{
    "090011": {
        "buy": 88.3, 
        "count": 4.0, 
        "deal": 88.4, 
        "diff": 0.5, 
        "sell": 88.4
    }, 
    "090016": {
        "buy": 88.3, 
        "count": 1.0, 
        "deal": 88.4, 
        "diff": 0.5, 
        "sell": 88.4
    }, 
    "090021": {
        "buy": 88.3, 
        "count": 3.0, 
        "deal": 88.4, 
        "diff": 0.5, 
        "sell": 88.4
    }, 
    "090026": {
        "buy": 88.3, 
        "count": 2.0, 
        "deal": 88.4, 
        "diff": 0.5, 
        "sell": 88.5
    }, 
    "090036": {
        "buy": 88.4, 
        "count": 1.0, 
        "deal": 88.5, 
        "diff": 0.6, 
        "sell": 88.5
    }, 
    "090041": {
        "buy": 88.4, 
        "count": 1.0, 
        "deal": 88.4, 
        "diff": 0.5, 
        "sell": 88.5
    }, 
    "090046": {
        "buy": 88.4, 
        "count": 1.0, 
        "deal": 88.4, 
        "diff": 0.5, 
        "sell": 88.5
    }, 
    "090051": {
        "buy": 88.4, 
        "count": 2.0, 
        "deal": 88.4, 
        "diff": 0.5, 
        "sell": 88.5
    }, 
    "090056": {
        "buy": 88.4, 
        "count": 1.0, 
        "deal": 88.4, 
        "diff": 0.5, 
        "sell": 88.5
    }, 
    "090101": {
        "buy": 88.4, 
        "count": 2.0, 
        "deal": 88.5, 
        "diff": 0.6, 
        "sell": 88.5
    }, 
    "090106": {
        "buy": 88.4, 
        "count": 4.0, 
        "deal": 88.4, 
        "diff": 0.5, 
        "sell": 88.5
    }, 
    "090111": {
        "buy": 88.4, 
        "count": 4.0, 
        "deal": 88.5, 
        "diff": 0.6, 
        "sell": 88.5
    }, 
    "090147": {
        "buy": 88.4, 
        "count": 2.0, 
        "deal": 88.5, 
        "diff": 0.6, 
        "sell": 88.5
    }, 
    "090152": {
        "buy": 88.4, 
        "count": 1.0, 
        "deal": 88.5, 
        "diff": 0.6, 
        "sell": 88.5
    }, 
    "090202": {
        "buy": 88.4, 
        "count": 1.0, 
        "deal": 88.5, 
        "diff": 0.6, 
        "sell": 88.5
    }, 
    "090207": {
        "buy": 88.4, 
        "count": 3.0, 
        "deal": 88.5, 
        "diff": 0.6, 
        "sell": 88.5
    }, 
    "090232": {
        "buy": 88.5, 
        "count": 2.0, 
        "deal": 88.5, 
        "diff": 0.6, 
        "sell": 88.6
    }, 
    "090237": {
        "buy": 88.5, 
        "count": 1.0, 
        "deal": 88.6, 
        "diff": 0.7, 
        "sell": 88.6
    }, 
    "090242": {
        "buy": 88.5, 
        "count": 5.0, 
        "deal": 88.6, 
        "diff": 0.7, 
        "sell": 88.6
    }, 
    "090247": {
        "buy": 88.5, 
        "count": 1.0, 
        "deal": 88.5, 
        "diff": 0.6, 
        "sell": 88.7
    }, 
    "090257": {
        "buy": 88.6, 
        "count": 1.0, 
        "deal": 88.6, 
        "diff": 0.7, 
        "sell": 88.7
    }, 
    "090302": {
        "buy": 88.5, 
        "count": 4.0, 
        "deal": 88.5, 
        "diff": 0.6, 
        "sell": 88.7
    }, 
    "090307": {
        "buy": 88.5, 
        "count": 1.0, 
        "deal": 88.6, 
        "diff": 0.7, 
        "sell": 88.6
    }, 
    "090327": {
        "buy": 88.5, 
        "count": 7.0, 
        "deal": 88.5, 
        "diff": 0.6, 
        "sell": 88.6
    }, 
    "090332": {
        "buy": 88.4, 
        "count": 2.0, 
        "deal": 88.4, 
        "diff": 0.5, 
        "sell": 88.6
    }, 
    "090337": {
        "buy": 88.4, 
        "count": 2.0, 
        "deal": 88.4, 
        "diff": 0.5, 
        "sell": 88.6
    }, 
    "090342": {
        "buy": 88.3, 
        "count": 1.0, 
        "deal": 88.3, 
        "diff": 0.4, 
        "sell": 88.5
    }, 
    "090347": {
        "buy": 88.3, 
        "count": 6.0, 
        "deal": 88.3, 
        "diff": 0.4, 
        "sell": 88.5
    }, 
    "090352": {
        "buy": 88.2, 
        "count": 1.0, 
        "deal": 88.3, 
        "diff": 0.4, 
        "sell": 88.4
    }, 
    "090357": {
        "buy": 88.2, 
        "count": 9.0, 
        "deal": 88.2, 
        "diff": 0.3, 
        "sell": 88.4
    }, 
    "090402": {
        "buy": 88.1, 
        "count": 1.0, 
        "deal": 88.1, 
        "diff": 0.2, 
        "sell": 88.4
    }, 
    "090408": {
        "buy": 88.1, 
        "count": 7.0, 
        "deal": 88.1, 
        "diff": 0.2, 
        "sell": 88.4
    }, 
    "090413": {
        "buy": 88.0, 
        "count": 1.0, 
        "deal": 88.0, 
        "diff": 0.1, 
        "sell": 88.4
    }, 
    "090418": {
        "buy": 88.0, 
        "count": 22.0, 
        "deal": 88.0, 
        "diff": 0.1, 
        "sell": 88.4
    }, 
    "090428": {
        "buy": 87.9, 
        "count": 15.0, 
        "deal": 87.9, 
        "diff": 0.0, 
        "sell": 88.1
    }, 
    "090433": {
        "buy": 87.9, 
        "count": 19.0, 
        "deal": 87.9, 
        "diff": 0.0, 
        "sell": 88.1
    }, 
    "090438": {
        "buy": 87.9, 
        "count": 2.0, 
        "deal": 87.9, 
        "diff": 0.0, 
        "sell": 88.1
    }, 
    "090443": {
        "buy": 87.8, 
        "count": 1.0, 
        "deal": 87.9, 
        "diff": 0.0, 
        "sell": 87.9
    }, 
    "090508": {
        "buy": 87.8, 
        "count": 9.0, 
        "deal": 87.8, 
        "diff": -0.1, 
        "sell": 87.9
    }, 
    "090528": {
        "buy": 87.8, 
        "count": 6.0, 
        "deal": 87.7, 
        "diff": -0.2, 
        "sell": 87.9
    }, 
    "090533": {
        "buy": 87.7, 
        "count": 1.0, 
        "deal": 87.7, 
        "diff": -0.2, 
        "sell": 87.8
    }, 
    "090538": {
        "buy": 87.6, 
        "count": 1.0, 
        "deal": 87.7, 
        "diff": -0.2, 
        "sell": 87.7
    }, 
    "090543": {
        "buy": 87.6, 
        "count": 4.0, 
        "deal": 87.6, 
        "diff": -0.3, 
        "sell": 87.8
    }, 
    "090553": {
        "buy": 87.6, 
        "count": 6.0, 
        "deal": 87.5, 
        "diff": -0.4, 
        "sell": 87.8
    }, 
    "090558": {
        "buy": 87.5, 
        "count": 2.0, 
        "deal": 87.5, 
        "diff": -0.4, 
        "sell": 87.8
    }, 
    "090603": {
        "buy": 87.5, 
        "count": 2.0, 
        "deal": 87.5, 
        "diff": -0.4, 
        "sell": 87.8
    }, 
    "090618": {
        "buy": 87.5, 
        "count": 2.0, 
        "deal": 87.5, 
        "diff": -0.4, 
        "sell": 87.8
    }, 
    "090653": {
        "buy": 87.5, 
        "count": 1.0, 
        "deal": 87.5, 
        "diff": -0.4, 
        "sell": 87.8
    }, 
    "090658": {
        "buy": 87.5, 
        "count": 1.0, 
        "deal": 87.5, 
        "diff": -0.4, 
        "sell": 87.8
    }, 
    "090718": {
        "buy": 87.5, 
        "count": 6.0, 
        "deal": 87.8, 
        "diff": -0.1, 
        "sell": 87.8
    }, 
    "090748": {
        "buy": 87.8, 
        "count": 1.0, 
        "deal": 87.9, 
        "diff": 0.0, 
        "sell": 87.9
    }, 
    "090828": {
        "buy": 87.9, 
        "count": 1.0, 
        "deal": 88.0, 
        "diff": 0.1, 
        "sell": 88.3
    }, 
    "090833": {
        "buy": 87.9, 
        "count": 10.0, 
        "deal": 87.9, 
        "diff": 0.0, 
        "sell": 88.3
    }, 
    "090919": {
        "buy": 88.0, 
        "count": 1.0, 
        "deal": 87.9, 
        "diff": 0.0, 
        "sell": 88.3
    }, 
    "090924": {
        "buy": 87.9, 
        "count": 2.0, 
        "deal": 87.9, 
        "diff": 0.0, 
        "sell": 88.0
    }, 
    "090944": {
        "buy": 87.8, 
        "count": 1.0, 
        "deal": 87.9, 
        "diff": 0.0, 
        "sell": 87.9
    }, 
    "091009": {
        "buy": 87.8, 
        "count": 2.0, 
        "deal": 87.8, 
        "diff": -0.1, 
        "sell": 87.9
    }, 
    "091039": {
        "buy": 87.7, 
        "count": 2.0, 
        "deal": 87.8, 
        "diff": -0.1, 
        "sell": 87.8
    }, 
    "091049": {
        "buy": 87.7, 
        "count": 5.0, 
        "deal": 87.8, 
        "diff": -0.1, 
        "sell": 87.8
    }, 
    "091059": {
        "buy": 87.7, 
        "count": 4.0, 
        "deal": 87.7, 
        "diff": -0.2, 
        "sell": 87.8
    }, 
    "091104": {
        "buy": 87.7, 
        "count": 5.0, 
        "deal": 87.8, 
        "diff": -0.1, 
        "sell": 87.8
    }, 
    "091224": {
        "buy": 87.8, 
        "count": 2.0, 
        "deal": 87.8, 
        "diff": -0.1, 
        "sell": 88.3
    }, 
    "091350": {
        "buy": 87.8, 
        "count": 1.0, 
        "deal": 87.8, 
        "diff": -0.1, 
        "sell": 88.1
    }, 
    "091431": {
        "buy": 87.8, 
        "count": 1.0, 
        "deal": 87.8, 
        "diff": -0.1, 
        "sell": 88.1
    }, 
    "091436": {
        "buy": 87.8, 
        "count": 1.0, 
        "deal": 87.8, 
        "diff": -0.1, 
        "sell": 88.1
    }, 
    "091451": {
        "buy": 87.8, 
        "count": 1.0, 
        "deal": 87.8, 
        "diff": -0.1, 
        "sell": 88.1
    }, 
    "091511": {
        "buy": 87.8, 
        "count": 3.0, 
        "deal": 87.8, 
        "diff": -0.1, 
        "sell": 88.1
    }, 
    "091656": {
        "buy": 87.9, 
        "count": 1.0, 
        "deal": 87.9, 
        "diff": 0.0, 
        "sell": 88.1
    }, 
    "091751": {
        "buy": 87.9, 
        "count": 2.0, 
        "deal": 87.9, 
        "diff": 0.0, 
        "sell": 88.1
    }, 
    "091826": {
        "buy": 87.9, 
        "count": 7.0, 
        "deal": 87.9, 
        "diff": 0.0, 
        "sell": 88.1
    }, 
    "091856": {
        "buy": 87.8, 
        "count": 8.0, 
        "deal": 87.8, 
        "diff": -0.1, 
        "sell": 87.9
    }, 
    "091957": {
        "buy": 87.7, 
        "count": 7.0, 
        "deal": 87.7, 
        "diff": -0.2, 
        "sell": 87.9
    }, 
    "092022": {
        "buy": 87.6, 
        "count": 1.0, 
        "deal": 87.6, 
        "diff": -0.3, 
        "sell": 87.9
    }, 
    "092032": {
        "buy": 87.6, 
        "count": 1.0, 
        "deal": 87.6, 
        "diff": -0.3, 
        "sell": 87.9
    }, 
    "092057": {
        "buy": 87.6, 
        "count": 4.0, 
        "deal": 87.6, 
        "diff": -0.3, 
        "sell": 87.9
    }, 
    "092117": {
        "buy": 87.5, 
        "count": 6.0, 
        "deal": 87.5, 
        "diff": -0.4, 
        "sell": 87.6
    }, 
    "092137": {
        "buy": 87.4, 
        "count": 1.0, 
        "deal": 87.4, 
        "diff": -0.5, 
        "sell": 87.6
    }, 
    "092152": {
        "buy": 87.4, 
        "count": 2.0, 
        "deal": 87.4, 
        "diff": -0.5, 
        "sell": 87.6
    }, 
    "092157": {
        "buy": 87.4, 
        "count": 2.0, 
        "deal": 87.4, 
        "diff": -0.5, 
        "sell": 87.5
    }, 
    "092212": {
        "buy": 87.3, 
        "count": 1.0, 
        "deal": 87.4, 
        "diff": -0.5, 
        "sell": 87.4
    }, 
    "092227": {
        "buy": 87.3, 
        "count": 2.0, 
        "deal": 87.3, 
        "diff": -0.6, 
        "sell": 87.4
    }, 
    "092232": {
        "buy": 87.3, 
        "count": 2.0, 
        "deal": 87.3, 
        "diff": -0.6, 
        "sell": 87.4
    }, 
    "092237": {
        "buy": 87.2, 
        "count": 1.0, 
        "deal": 87.3, 
        "diff": -0.6, 
        "sell": 87.3
    }, 
    "092242": {
        "buy": 87.2, 
        "count": 1.0, 
        "deal": 87.3, 
        "diff": -0.6, 
        "sell": 87.3
    }, 
    "092247": {
        "buy": 87.2, 
        "count": 5.0, 
        "deal": 87.3, 
        "diff": -0.6, 
        "sell": 87.3
    }, 
    "092257": {
        "buy": 87.2, 
        "count": 1.0, 
        "deal": 87.4, 
        "diff": -0.5, 
        "sell": 87.4
    }, 
    "092302": {
        "buy": 87.4, 
        "count": 4.0, 
        "deal": 87.2, 
        "diff": -0.7, 
        "sell": 87.6
    }, 
    "092307": {
        "buy": 87.2, 
        "count": 52.0, 
        "deal": 87.1, 
        "diff": -0.8, 
        "sell": 87.3
    }, 
    "092323": {
        "buy": 87.1, 
        "count": 1.0, 
        "deal": 87.1, 
        "diff": -0.8, 
        "sell": 87.3
    }, 
    "092328": {
        "buy": 87.1, 
        "count": 2.0, 
        "deal": 87.1, 
        "diff": -0.8, 
        "sell": 87.3
    }, 
    "092343": {
        "buy": 87.1, 
        "count": 1.0, 
        "deal": 87.1, 
        "diff": -0.8, 
        "sell": 87.3
    }, 
    "092418": {
        "buy": 87.1, 
        "count": 2.0, 
        "deal": 87.1, 
        "diff": -0.8, 
        "sell": 87.3
    }, 
    "092423": {
        "buy": 87.1, 
        "count": 3.0, 
        "deal": 87.1, 
        "diff": -0.8, 
        "sell": 87.3
    }, 
    "092428": {
        "buy": 87.0, 
        "count": 1.0, 
        "deal": 87.1, 
        "diff": -0.8, 
        "sell": 87.1
    }, 
    "092438": {
        "buy": 87.0, 
        "count": 1.0, 
        "deal": 87.1, 
        "diff": -0.8, 
        "sell": 87.1
    }, 
    "092514": {
        "buy": 87.0, 
        "count": 2.0, 
        "deal": 87.1, 
        "diff": -0.8, 
        "sell": 87.1
    }, 
    "092519": {
        "buy": 87.0, 
        "count": 1.0, 
        "deal": 87.1, 
        "diff": -0.8, 
        "sell": 87.1
    }, 
    "092549": {
        "buy": 87.1, 
        "count": 1.0, 
        "deal": 87.2, 
        "diff": -0.7, 
        "sell": 87.2
    }, 
    "092559": {
        "buy": 87.1, 
        "count": 3.0, 
        "deal": 87.0, 
        "diff": -0.9, 
        "sell": 87.3
    }, 
    "092609": {
        "buy": 87.2, 
        "count": 1.0, 
        "deal": 87.2, 
        "diff": -0.7, 
        "sell": 87.3
    }, 
    "092614": {
        "buy": 87.2, 
        "count": 1.0, 
        "deal": 87.2, 
        "diff": -0.7, 
        "sell": 87.3
    }, 
    "092619": {
        "buy": 87.2, 
        "count": 1.0, 
        "deal": 87.2, 
        "diff": -0.7, 
        "sell": 87.3
    }, 
    "092754": {
        "buy": 87.2, 
        "count": 1.0, 
        "deal": 87.2, 
        "diff": -0.7, 
        "sell": 87.3
    }, 
    "092804": {
        "buy": 87.2, 
        "count": 5.0, 
        "deal": 87.3, 
        "diff": -0.6, 
        "sell": 87.3
    }, 
    "092809": {
        "buy": 87.2, 
        "count": 1.0, 
        "deal": 87.7, 
        "diff": -0.2, 
        "sell": 87.4
    }, 
    "092849": {
        "buy": 87.3, 
        "count": 3.0, 
        "deal": 87.3, 
        "diff": -0.6, 
        "sell": 87.6
    }, 
    "093035": {
        "buy": 87.3, 
        "count": 2.0, 
        "deal": 87.3, 
        "diff": -0.6, 
        "sell": 87.5
    }, 
    "093050": {
        "buy": 87.3, 
        "count": 1.0, 
        "deal": 87.3, 
        "diff": -0.6, 
        "sell": 87.5
    }, 
    "093100": {
        "buy": 87.3, 
        "count": 3.0, 
        "deal": 87.3, 
        "diff": -0.6, 
        "sell": 87.5
    }, 
    "093320": {
        "buy": 87.3, 
        "count": 5.0, 
        "deal": 87.3, 
        "diff": -0.6, 
        "sell": 87.5
    }, 
    "093421": {
        "buy": 87.4, 
        "count": 1.0, 
        "deal": 87.4, 
        "diff": -0.5, 
        "sell": 87.5
    }, 
    "093426": {
        "buy": 87.4, 
        "count": 1.0, 
        "deal": 87.4, 
        "diff": -0.5, 
        "sell": 87.5
    }, 
    "093501": {
        "buy": 87.4, 
        "count": 1.0, 
        "deal": 87.4, 
        "diff": -0.5, 
        "sell": 87.5
    }, 
    "093606": {
        "buy": 87.3, 
        "count": 1.0, 
        "deal": 87.4, 
        "diff": -0.5, 
        "sell": 87.4
    }, 
    "093647": {
        "buy": 87.3, 
        "count": 2.0, 
        "deal": 87.4, 
        "diff": -0.5, 
        "sell": 87.4
    }, 
    "093657": {
        "buy": 87.3, 
        "count": 5.0, 
        "deal": 87.4, 
        "diff": -0.5, 
        "sell": 87.4
    }, 
    "093702": {
        "buy": 87.3, 
        "count": 1.0, 
        "deal": 87.4, 
        "diff": -0.5, 
        "sell": 87.4
    }, 
    "093812": {
        "buy": 87.3, 
        "count": 1.0, 
        "deal": 87.3, 
        "diff": -0.6, 
        "sell": 87.4
    }, 
    "093847": {
        "buy": 87.3, 
        "count": 1.0, 
        "deal": 87.4, 
        "diff": -0.5, 
        "sell": 87.4
    }, 
    "093902": {
        "buy": 87.3, 
        "count": 2.0, 
        "deal": 87.4, 
        "diff": -0.5, 
        "sell": 87.4
    }, 
    "093917": {
        "buy": 87.3, 
        "count": 3.0, 
        "deal": 87.3, 
        "diff": -0.6, 
        "sell": 87.4
    }, 
    "094007": {
        "buy": 87.3, 
        "count": 1.0, 
        "deal": 87.4, 
        "diff": -0.5, 
        "sell": 87.4
    }, 
    "094022": {
        "buy": 87.3, 
        "count": 3.0, 
        "deal": 87.3, 
        "diff": -0.6, 
        "sell": 87.4
    }, 
    "094027": {
        "buy": 87.3, 
        "count": 2.0, 
        "deal": 87.3, 
        "diff": -0.6, 
        "sell": 87.4
    }, 
    "094037": {
        "buy": 87.2, 
        "count": 1.0, 
        "deal": 87.2, 
        "diff": -0.7, 
        "sell": 87.3
    }, 
    "094042": {
        "buy": 87.2, 
        "count": 1.0, 
        "deal": 87.2, 
        "diff": -0.7, 
        "sell": 87.3
    }, 
    "094053": {
        "buy": 87.2, 
        "count": 2.0, 
        "deal": 87.2, 
        "diff": -0.7, 
        "sell": 87.3
    }, 
    "094058": {
        "buy": 87.2, 
        "count": 6.0, 
        "deal": 87.2, 
        "diff": -0.7, 
        "sell": 87.3
    }, 
    "094128": {
        "buy": 87.1, 
        "count": 3.0, 
        "deal": 87.1, 
        "diff": -0.8, 
        "sell": 87.2
    }, 
    "094133": {
        "buy": 87.1, 
        "count": 3.0, 
        "deal": 87.1, 
        "diff": -0.8, 
        "sell": 87.2
    }, 
    "094138": {
        "buy": 87.1, 
        "count": 1.0, 
        "deal": 87.1, 
        "diff": -0.8, 
        "sell": 87.2
    }, 
    "094158": {
        "buy": 87.1, 
        "count": 1.0, 
        "deal": 87.2, 
        "diff": -0.7, 
        "sell": 87.2
    }, 
    "094203": {
        "buy": 87.1, 
        "count": 6.0, 
        "deal": 87.0, 
        "diff": -0.9, 
        "sell": 87.2
    }, 
    "094208": {
        "buy": 87.0, 
        "count": 21.0, 
        "deal": 87.0, 
        "diff": -0.9, 
        "sell": 87.2
    }, 
    "094213": {
        "buy": 86.9, 
        "count": 1.0, 
        "deal": 86.9, 
        "diff": -1.0, 
        "sell": 87.2
    }, 
    "094218": {
        "buy": 86.9, 
        "count": 1.0, 
        "deal": 86.9, 
        "diff": -1.0, 
        "sell": 87.1
    }, 
    "094223": {
        "buy": 86.9, 
        "count": 2.0, 
        "deal": 86.9, 
        "diff": -1.0, 
        "sell": 87.1
    }, 
    "094233": {
        "buy": 86.8, 
        "count": 3.0, 
        "deal": 86.8, 
        "diff": -1.1, 
        "sell": 86.9
    }, 
    "094238": {
        "buy": 86.6, 
        "count": 1.0, 
        "deal": 86.6, 
        "diff": -1.3, 
        "sell": 86.8
    }, 
    "094243": {
        "buy": 86.5, 
        "count": 3.0, 
        "deal": 86.5, 
        "diff": -1.4, 
        "sell": 86.9
    }, 
    "094248": {
        "buy": 86.5, 
        "count": 1.0, 
        "deal": 86.8, 
        "diff": -1.1, 
        "sell": 86.8
    }, 
    "094303": {
        "buy": 86.5, 
        "count": 1.0, 
        "deal": 86.6, 
        "diff": -1.3, 
        "sell": 86.8
    }, 
    "094328": {
        "buy": 86.6, 
        "count": 1.0, 
        "deal": 86.6, 
        "diff": -1.3, 
        "sell": 86.8
    }, 
    "094333": {
        "buy": 86.6, 
        "count": 1.0, 
        "deal": 86.6, 
        "diff": -1.3, 
        "sell": 86.8
    }, 
    "094338": {
        "buy": 86.5, 
        "count": 1.0, 
        "deal": 86.6, 
        "diff": -1.3, 
        "sell": 86.8
    }, 
    "094353": {
        "buy": 86.5, 
        "count": 1.0, 
        "deal": 86.6, 
        "diff": -1.3, 
        "sell": 86.6
    }, 
    "094358": {
        "buy": 86.5, 
        "count": 2.0, 
        "deal": 86.6, 
        "diff": -1.3, 
        "sell": 86.6
    }, 
    "094409": {
        "buy": 86.6, 
        "count": 1.0, 
        "deal": 86.6, 
        "diff": -1.3, 
        "sell": 86.7
    }, 
    "094414": {
        "buy": 86.6, 
        "count": 1.0, 
        "deal": 86.7, 
        "diff": -1.2, 
        "sell": 86.7
    }, 
    "094434": {
        "buy": 86.6, 
        "count": 5.0, 
        "deal": 86.7, 
        "diff": -1.2, 
        "sell": 86.7
    }, 
    "094439": {
        "buy": 86.6, 
        "count": 1.0, 
        "deal": 86.7, 
        "diff": -1.2, 
        "sell": 86.7
    }, 
    "094444": {
        "buy": 86.6, 
        "count": 2.0, 
        "deal": 86.8, 
        "diff": -1.1, 
        "sell": 86.8
    }, 
    "094454": {
        "buy": 86.7, 
        "count": 1.0, 
        "deal": 86.9, 
        "diff": -1.0, 
        "sell": 86.9
    }, 
    "094459": {
        "buy": 86.7, 
        "count": 1.0, 
        "deal": 86.9, 
        "diff": -1.0, 
        "sell": 87.0
    }, 
    "094514": {
        "buy": 86.9, 
        "count": 1.0, 
        "deal": 86.9, 
        "diff": -1.0, 
        "sell": 87.0
    }, 
    "094519": {
        "buy": 86.7, 
        "count": 1.0, 
        "deal": 86.9, 
        "diff": -1.0, 
        "sell": 86.9
    }, 
    "094529": {
        "buy": 86.9, 
        "count": 3.0, 
        "deal": 86.9, 
        "diff": -1.0, 
        "sell": 87.0
    }, 
    "094534": {
        "buy": 86.8, 
        "count": 2.0, 
        "deal": 86.9, 
        "diff": -1.0, 
        "sell": 87.0
    }, 
    "094539": {
        "buy": 86.8, 
        "count": 3.0, 
        "deal": 86.8, 
        "diff": -1.1, 
        "sell": 86.9
    }, 
    "094549": {
        "buy": 86.7, 
        "count": 2.0, 
        "deal": 86.7, 
        "diff": -1.2, 
        "sell": 86.9
    }, 
    "094559": {
        "buy": 86.8, 
        "count": 2.0, 
        "deal": 86.7, 
        "diff": -1.2, 
        "sell": 86.9
    }, 
    "094704": {
        "buy": 86.8, 
        "count": 1.0, 
        "deal": 86.8, 
        "diff": -1.1, 
        "sell": 86.9
    }, 
    "094714": {
        "buy": 86.8, 
        "count": 3.0, 
        "deal": 86.8, 
        "diff": -1.1, 
        "sell": 86.9
    }, 
    "094724": {
        "buy": 86.8, 
        "count": 1.0, 
        "deal": 86.8, 
        "diff": -1.1, 
        "sell": 86.9
    }, 
    "094739": {
        "buy": 86.8, 
        "count": 4.0, 
        "deal": 86.8, 
        "diff": -1.1, 
        "sell": 86.9
    }, 
    "094744": {
        "buy": 86.8, 
        "count": 2.0, 
        "deal": 86.8, 
        "diff": -1.1, 
        "sell": 86.9
    }, 
    "094755": {
        "buy": 86.8, 
        "count": 1.0, 
        "deal": 86.9, 
        "diff": -1.0, 
        "sell": 86.9
    }, 
    "094810": {
        "buy": 86.8, 
        "count": 2.0, 
        "deal": 86.8, 
        "diff": -1.1, 
        "sell": 86.9
    }, 
    "094815": {
        "buy": 86.8, 
        "count": 4.0, 
        "deal": 86.9, 
        "diff": -1.0, 
        "sell": 86.9
    }, 
    "094825": {
        "buy": 86.9, 
        "count": 1.0, 
        "deal": 87.0, 
        "diff": -0.9, 
        "sell": 87.0
    }, 
    "094835": {
        "buy": 86.9, 
        "count": 1.0, 
        "deal": 87.0, 
        "diff": -0.9, 
        "sell": 87.0
    }, 
    "094850": {
        "buy": 86.9, 
        "count": 2.0, 
        "deal": 87.0, 
        "diff": -0.9, 
        "sell": 87.0
    }, 
    "094910": {
        "buy": 86.9, 
        "count": 4.0, 
        "deal": 87.0, 
        "diff": -0.9, 
        "sell": 87.0
    }, 
    "094935": {
        "buy": 87.0, 
        "count": 1.0, 
        "deal": 87.1, 
        "diff": -0.8, 
        "sell": 87.1
    }, 
    "094940": {
        "buy": 87.0, 
        "count": 1.0, 
        "deal": 87.0, 
        "diff": -0.9, 
        "sell": 87.1
    }, 
    "095010": {
        "buy": 87.0, 
        "count": 3.0, 
        "deal": 87.1, 
        "diff": -0.8, 
        "sell": 87.1
    }, 
    "095055": {
        "buy": 87.0, 
        "count": 1.0, 
        "deal": 87.3, 
        "diff": -0.6, 
        "sell": 87.3
    }, 
    "095211": {
        "buy": 87.1, 
        "count": 2.0, 
        "deal": 87.1, 
        "diff": -0.8, 
        "sell": 87.3
    }, 
    "095326": {
        "buy": 87.1, 
        "count": 7.0, 
        "deal": 87.0, 
        "diff": -0.9, 
        "sell": 87.3
    }, 
    "095331": {
        "buy": 86.9, 
        "count": 2.0, 
        "deal": 86.9, 
        "diff": -1.0, 
        "sell": 87.0
    }, 
    "095351": {
        "buy": 86.9, 
        "count": 1.0, 
        "deal": 87.0, 
        "diff": -0.9, 
        "sell": 87.0
    }, 
    "095356": {
        "buy": 86.9, 
        "count": 2.0, 
        "deal": 87.0, 
        "diff": -0.9, 
        "sell": 87.0
    }, 
    "095401": {
        "buy": 86.9, 
        "count": 1.0, 
        "deal": 87.0, 
        "diff": -0.9, 
        "sell": 87.0
    }, 
    "095417": {
        "buy": 86.9, 
        "count": 1.0, 
        "deal": 87.0, 
        "diff": -0.9, 
        "sell": 87.0
    }, 
    "095422": {
        "buy": 86.9, 
        "count": 6.0, 
        "deal": 87.0, 
        "diff": -0.9, 
        "sell": 87.0
    }, 
    "095437": {
        "buy": 87.0, 
        "count": 1.0, 
        "deal": 87.1, 
        "diff": -0.8, 
        "sell": 87.1
    }, 
    "095617": {
        "buy": 87.1, 
        "count": 1.0, 
        "deal": 87.1, 
        "diff": -0.8, 
        "sell": 87.3
    }, 
    "095622": {
        "buy": 87.1, 
        "count": 1.0, 
        "deal": 87.1, 
        "diff": -0.8, 
        "sell": 87.3
    }, 
    "095642": {
        "buy": 87.0, 
        "count": 5.0, 
        "deal": 87.0, 
        "diff": -0.9, 
        "sell": 87.1
    }, 
    "095652": {
        "buy": 87.0, 
        "count": 1.0, 
        "deal": 87.0, 
        "diff": -0.9, 
        "sell": 87.1
    }, 
    "095712": {
        "buy": 87.0, 
        "count": 1.0, 
        "deal": 87.0, 
        "diff": -0.9, 
        "sell": 87.1
    }, 
    "095757": {
        "buy": 86.9, 
        "count": 1.0, 
        "deal": 86.9, 
        "diff": -1.0, 
        "sell": 87.1
    }, 
    "095822": {
        "buy": 86.9, 
        "count": 1.0, 
        "deal": 86.9, 
        "diff": -1.0, 
        "sell": 87.1
    }, 
    "095832": {
        "buy": 86.9, 
        "count": 1.0, 
        "deal": 86.9, 
        "diff": -1.0, 
        "sell": 87.1
    }, 
    "095842": {
        "buy": 86.9, 
        "count": 1.0, 
        "deal": 86.9, 
        "diff": -1.0, 
        "sell": 87.1
    }, 
    "095913": {
        "buy": 86.9, 
        "count": 3.0, 
        "deal": 86.9, 
        "diff": -1.0, 
        "sell": 87.1
    }, 
    "095918": {
        "buy": 86.9, 
        "count": 2.0, 
        "deal": 86.9, 
        "diff": -1.0, 
        "sell": 87.1
    }, 
    "095923": {
        "buy": 86.8, 
        "count": 5.0, 
        "deal": 86.9, 
        "diff": -1.0, 
        "sell": 86.9
    }, 
    "095928": {
        "buy": 86.8, 
        "count": 1.0, 
        "deal": 86.8, 
        "diff": -1.1, 
        "sell": 87.1
    }, 
    "095938": {
        "buy": 86.8, 
        "count": 3.0, 
        "deal": 86.8, 
        "diff": -1.1, 
        "sell": 87.1
    }, 
    "095943": {
        "buy": 86.8, 
        "count": 1.0, 
        "deal": 86.8, 
        "diff": -1.1, 
        "sell": 87.1
    }, 
    "095948": {
        "buy": 86.8, 
        "count": 1.0, 
        "deal": 87.1, 
        "diff": -0.8, 
        "sell": 87.1
    }, 
    "095953": {
        "buy": 86.8, 
        "count": 2.0, 
        "deal": 86.8, 
        "diff": -1.1, 
        "sell": 87.1
    }, 
    "100003": {
        "buy": 86.8, 
        "count": 1.0, 
        "deal": 87.1, 
        "diff": -0.8, 
        "sell": 87.1
    }, 
    "100023": {
        "buy": 86.8, 
        "count": 5.0, 
        "deal": 86.7, 
        "diff": -1.2, 
        "sell": 87.0
    }, 
    "100028": {
        "buy": 86.7, 
        "count": 1.0, 
        "deal": 87.0, 
        "diff": -0.9, 
        "sell": 87.0
    }, 
    "100103": {
        "buy": 86.7, 
        "count": 1.0, 
        "deal": 87.0, 
        "diff": -0.9, 
        "sell": 87.0
    }, 
    "100138": {
        "buy": 86.8, 
        "count": 1.0, 
        "deal": 87.0, 
        "diff": -0.9, 
        "sell": 87.0
    }, 
    "100153": {
        "buy": 86.8, 
        "count": 1.0, 
        "deal": 87.0, 
        "diff": -0.9, 
        "sell": 87.0
    }, 
    "100208": {
        "buy": 87.0, 
        "count": 1.0, 
        "deal": 87.0, 
        "diff": -0.9, 
        "sell": 87.1
    }, 
    "100213": {
        "buy": 86.8, 
        "count": 2.0, 
        "deal": 86.8, 
        "diff": -1.1, 
        "sell": 87.0
    }, 
    "100218": {
        "buy": 86.7, 
        "count": 1.0, 
        "deal": 87.1, 
        "diff": -0.8, 
        "sell": 87.1
    }, 
    "100243": {
        "buy": 86.7, 
        "count": 1.0, 
        "deal": 87.1, 
        "diff": -0.8, 
        "sell": 87.1
    }, 
    "100415": {
        "buy": 86.8, 
        "count": 1.0, 
        "deal": 86.8, 
        "diff": -1.1, 
        "sell": 87.0
    }, 
    "100545": {
        "buy": 86.9, 
        "count": 1.0, 
        "deal": 87.0, 
        "diff": -0.9, 
        "sell": 87.0
    }, 
    "100550": {
        "buy": 86.9, 
        "count": 1.0, 
        "deal": 87.0, 
        "diff": -0.9, 
        "sell": 87.0
    }, 
    "100600": {
        "buy": 86.9, 
        "count": 1.0, 
        "deal": 87.0, 
        "diff": -0.9, 
        "sell": 87.0
    }, 
    "100820": {
        "buy": 87.0, 
        "count": 1.0, 
        "deal": 87.1, 
        "diff": -0.8, 
        "sell": 87.1
    }, 
    "100840": {
        "buy": 87.0, 
        "count": 1.0, 
        "deal": 87.1, 
        "diff": -0.8, 
        "sell": 87.1
    }, 
    "100946": {
        "buy": 87.0, 
        "count": 1.0, 
        "deal": 87.1, 
        "diff": -0.8, 
        "sell": 87.1
    }, 
    "101011": {
        "buy": 87.0, 
        "count": 1.0, 
        "deal": 87.0, 
        "diff": -0.9, 
        "sell": 87.1
    }, 
    "101041": {
        "buy": 87.0, 
        "count": 1.0, 
        "deal": 87.0, 
        "diff": -0.9, 
        "sell": 87.1
    }, 
    "101131": {
        "buy": 87.0, 
        "count": 1.0, 
        "deal": 87.1, 
        "diff": -0.8, 
        "sell": 87.1
    }, 
    "101136": {
        "buy": 87.0, 
        "count": 1.0, 
        "deal": 87.0, 
        "diff": -0.9, 
        "sell": 87.1
    }, 
    "101141": {
        "buy": 87.0, 
        "count": 1.0, 
        "deal": 87.1, 
        "diff": -0.8, 
        "sell": 87.1
    }, 
    "101236": {
        "buy": 87.0, 
        "count": 1.0, 
        "deal": 87.0, 
        "diff": -0.9, 
        "sell": 87.1
    }, 
    "101432": {
        "buy": 87.0, 
        "count": 2.0, 
        "deal": 87.0, 
        "diff": -0.9, 
        "sell": 87.1
    }, 
    "101437": {
        "buy": 87.0, 
        "count": 1.0, 
        "deal": 87.1, 
        "diff": -0.8, 
        "sell": 87.1
    }, 
    "101517": {
        "buy": 87.0, 
        "count": 5.0, 
        "deal": 87.0, 
        "diff": -0.9, 
        "sell": 87.1
    }, 
    "101538": {
        "buy": 87.0, 
        "count": 1.0, 
        "deal": 87.0, 
        "diff": -0.9, 
        "sell": 87.1
    }, 
    "101613": {
        "buy": 87.0, 
        "count": 1.0, 
        "deal": 87.0, 
        "diff": -0.9, 
        "sell": 87.1
    }, 
    "101643": {
        "buy": 87.0, 
        "count": 1.0, 
        "deal": 87.1, 
        "diff": -0.8, 
        "sell": 87.1
    }, 
    "101718": {
        "buy": 87.0, 
        "count": 1.0, 
        "deal": 87.1, 
        "diff": -0.8, 
        "sell": 87.1
    }, 
    "101723": {
        "buy": 87.0, 
        "count": 1.0, 
        "deal": 87.0, 
        "diff": -0.9, 
        "sell": 87.1
    }, 
    "101728": {
        "buy": 87.0, 
        "count": 1.0, 
        "deal": 87.1, 
        "diff": -0.8, 
        "sell": 87.1
    }, 
    "101733": {
        "buy": 87.0, 
        "count": 1.0, 
        "deal": 87.1, 
        "diff": -0.8, 
        "sell": 87.1
    }, 
    "101758": {
        "buy": 87.0, 
        "count": 1.0, 
        "deal": 87.1, 
        "diff": -0.8, 
        "sell": 87.1
    }, 
    "101843": {
        "buy": 87.0, 
        "count": 1.0, 
        "deal": 87.1, 
        "diff": -0.8, 
        "sell": 87.1
    }, 
    "101913": {
        "buy": 87.0, 
        "count": 2.0, 
        "deal": 87.1, 
        "diff": -0.8, 
        "sell": 87.1
    }, 
    "101918": {
        "buy": 87.0, 
        "count": 2.0, 
        "deal": 87.1, 
        "diff": -0.8, 
        "sell": 87.1
    }, 
    "102019": {
        "buy": 87.1, 
        "count": 1.0, 
        "deal": 87.1, 
        "diff": -0.8, 
        "sell": 87.2
    }, 
    "102034": {
        "buy": 87.1, 
        "count": 1.0, 
        "deal": 87.2, 
        "diff": -0.7, 
        "sell": 87.2
    }, 
    "102144": {
        "buy": 87.1, 
        "count": 1.0, 
        "deal": 87.2, 
        "diff": -0.7, 
        "sell": 87.2
    }, 
    "102304": {
        "buy": 87.1, 
        "count": 1.0, 
        "deal": 87.2, 
        "diff": -0.7, 
        "sell": 87.2
    }, 
    "102329": {
        "buy": 87.1, 
        "count": 1.0, 
        "deal": 87.2, 
        "diff": -0.7, 
        "sell": 87.2
    }, 
    "102410": {
        "buy": 87.1, 
        "count": 5.0, 
        "deal": 87.1, 
        "diff": -0.8, 
        "sell": 87.2
    }, 
    "102450": {
        "buy": 87.1, 
        "count": 1.0, 
        "deal": 87.1, 
        "diff": -0.8, 
        "sell": 87.2
    }, 
    "102500": {
        "buy": 87.1, 
        "count": 1.0, 
        "deal": 87.1, 
        "diff": -0.8, 
        "sell": 87.2
    }, 
    "102630": {
        "buy": 87.1, 
        "count": 1.0, 
        "deal": 87.2, 
        "diff": -0.7, 
        "sell": 87.2
    }, 
    "102836": {
        "buy": 87.1, 
        "count": 1.0, 
        "deal": 87.1, 
        "diff": -0.8, 
        "sell": 87.2
    }, 
    "102846": {
        "buy": 87.1, 
        "count": 1.0, 
        "deal": 87.2, 
        "diff": -0.7, 
        "sell": 87.2
    }, 
    "102926": {
        "buy": 87.1, 
        "count": 1.0, 
        "deal": 87.2, 
        "diff": -0.7, 
        "sell": 87.2
    }, 
    "103031": {
        "buy": 87.1, 
        "count": 4.0, 
        "deal": 87.1, 
        "diff": -0.8, 
        "sell": 87.2
    }, 
    "103036": {
        "buy": 87.1, 
        "count": 3.0, 
        "deal": 87.1, 
        "diff": -0.8, 
        "sell": 87.2
    }, 
    "103041": {
        "buy": 87.0, 
        "count": 5.0, 
        "deal": 87.0, 
        "diff": -0.9, 
        "sell": 87.1
    }, 
    "103227": {
        "buy": 87.0, 
        "count": 1.0, 
        "deal": 87.1, 
        "diff": -0.8, 
        "sell": 87.1
    }, 
    "103307": {
        "buy": 87.0, 
        "count": 2.0, 
        "deal": 87.0, 
        "diff": -0.9, 
        "sell": 87.1
    }, 
    "103433": {
        "buy": 87.0, 
        "count": 1.0, 
        "deal": 87.1, 
        "diff": -0.8, 
        "sell": 87.1
    }, 
    "103438": {
        "buy": 87.0, 
        "count": 1.0, 
        "deal": 87.0, 
        "diff": -0.9, 
        "sell": 87.1
    }, 
    "103523": {
        "buy": 87.0, 
        "count": 1.0, 
        "deal": 87.1, 
        "diff": -0.8, 
        "sell": 87.1
    }, 
    "103733": {
        "buy": 87.0, 
        "count": 1.0, 
        "deal": 87.0, 
        "diff": -0.9, 
        "sell": 87.1
    }, 
    "103819": {
        "buy": 87.0, 
        "count": 1.0, 
        "deal": 87.1, 
        "diff": -0.8, 
        "sell": 87.1
    }, 
    "103929": {
        "buy": 87.0, 
        "count": 1.0, 
        "deal": 87.1, 
        "diff": -0.8, 
        "sell": 87.1
    }, 
    "104019": {
        "buy": 87.0, 
        "count": 1.0, 
        "deal": 87.1, 
        "diff": -0.8, 
        "sell": 87.1
    }, 
    "104024": {
        "buy": 87.0, 
        "count": 3.0, 
        "deal": 87.1, 
        "diff": -0.8, 
        "sell": 87.1
    }, 
    "104119": {
        "buy": 87.0, 
        "count": 1.0, 
        "deal": 87.1, 
        "diff": -0.8, 
        "sell": 87.1
    }, 
    "104124": {
        "buy": 87.0, 
        "count": 1.0, 
        "deal": 87.1, 
        "diff": -0.8, 
        "sell": 87.1
    }, 
    "104129": {
        "buy": 87.0, 
        "count": 1.0, 
        "deal": 87.1, 
        "diff": -0.8, 
        "sell": 87.1
    }, 
    "104134": {
        "buy": 87.0, 
        "count": 1.0, 
        "deal": 87.1, 
        "diff": -0.8, 
        "sell": 87.1
    }, 
    "104144": {
        "buy": 87.0, 
        "count": 1.0, 
        "deal": 87.1, 
        "diff": -0.8, 
        "sell": 87.1
    }, 
    "104300": {
        "buy": 87.0, 
        "count": 3.0, 
        "deal": 87.0, 
        "diff": -0.9, 
        "sell": 87.2
    }, 
    "104345": {
        "buy": 87.0, 
        "count": 1.0, 
        "deal": 87.0, 
        "diff": -0.9, 
        "sell": 87.2
    }, 
    "104355": {
        "buy": 87.0, 
        "count": 1.0, 
        "deal": 87.0, 
        "diff": -0.9, 
        "sell": 87.2
    }, 
    "104416": {
        "buy": 87.0, 
        "count": 1.0, 
        "deal": 87.2, 
        "diff": -0.7, 
        "sell": 87.2
    }, 
    "104601": {
        "buy": 87.0, 
        "count": 1.0, 
        "deal": 87.1, 
        "diff": -0.8, 
        "sell": 87.1
    }, 
    "104651": {
        "buy": 87.0, 
        "count": 1.0, 
        "deal": 87.1, 
        "diff": -0.8, 
        "sell": 87.1
    }, 
    "104716": {
        "buy": 87.0, 
        "count": 1.0, 
        "deal": 87.2, 
        "diff": -0.7, 
        "sell": 87.2
    }, 
    "104836": {
        "buy": 87.1, 
        "count": 1.0, 
        "deal": 87.2, 
        "diff": -0.7, 
        "sell": 87.2
    }, 
    "104917": {
        "buy": 87.1, 
        "count": 4.0, 
        "deal": 87.1, 
        "diff": -0.8, 
        "sell": 87.2
    }, 
    "104927": {
        "buy": 87.0, 
        "count": 4.0, 
        "deal": 87.0, 
        "diff": -0.9, 
        "sell": 87.2
    }, 
    "104932": {
        "buy": 87.0, 
        "count": 1.0, 
        "deal": 87.0, 
        "diff": -0.9, 
        "sell": 87.2
    }, 
    "105012": {
        "buy": 86.8, 
        "count": 1.0, 
        "deal": 87.0, 
        "diff": -0.9, 
        "sell": 87.0
    }, 
    "105107": {
        "buy": 86.8, 
        "count": 2.0, 
        "deal": 86.8, 
        "diff": -1.1, 
        "sell": 87.0
    }, 
    "105137": {
        "buy": 86.8, 
        "count": 1.0, 
        "deal": 86.8, 
        "diff": -1.1, 
        "sell": 87.0
    }, 
    "105147": {
        "buy": 86.8, 
        "count": 1.0, 
        "deal": 87.0, 
        "diff": -0.9, 
        "sell": 87.0
    }, 
    "105152": {
        "buy": 86.8, 
        "count": 2.0, 
        "deal": 86.8, 
        "diff": -1.1, 
        "sell": 87.0
    }, 
    "105212": {
        "buy": 86.8, 
        "count": 2.0, 
        "deal": 86.8, 
        "diff": -1.1, 
        "sell": 87.0
    }, 
    "105217": {
        "buy": 86.8, 
        "count": 1.0, 
        "deal": 86.8, 
        "diff": -1.1, 
        "sell": 87.0
    }, 
    "105313": {
        "buy": 86.8, 
        "count": 1.0, 
        "deal": 87.0, 
        "diff": -0.9, 
        "sell": 87.0
    }, 
    "105414": {
        "buy": 86.8, 
        "count": 5.0, 
        "deal": 87.0, 
        "diff": -0.9, 
        "sell": 87.0
    }, 
    "105434": {
        "buy": 86.8, 
        "count": 4.0, 
        "deal": 87.0, 
        "diff": -0.9, 
        "sell": 87.0
    }, 
    "105439": {
        "buy": 87.0, 
        "count": 1.0, 
        "deal": 87.0, 
        "diff": -0.9, 
        "sell": 87.1
    }, 
    "105529": {
        "buy": 87.1, 
        "count": 1.0, 
        "deal": 87.1, 
        "diff": -0.8, 
        "sell": 87.2
    }, 
    "105534": {
        "buy": 87.1, 
        "count": 2.0, 
        "deal": 87.1, 
        "diff": -0.8, 
        "sell": 87.2
    }, 
    "105609": {
        "buy": 86.9, 
        "count": 1.0, 
        "deal": 87.2, 
        "diff": -0.7, 
        "sell": 87.2
    }, 
    "105734": {
        "buy": 86.9, 
        "count": 1.0, 
        "deal": 87.2, 
        "diff": -0.7, 
        "sell": 87.1
    }, 
    "105904": {
        "buy": 87.0, 
        "count": 1.0, 
        "deal": 87.2, 
        "diff": -0.7, 
        "sell": 87.2
    }, 
    "110205": {
        "buy": 87.0, 
        "count": 1.0, 
        "deal": 87.3, 
        "diff": -0.6, 
        "sell": 87.3
    }, 
    "110255": {
        "buy": 87.0, 
        "count": 3.0, 
        "deal": 87.3, 
        "diff": -0.6, 
        "sell": 87.3
    }, 
    "110320": {
        "buy": 87.0, 
        "count": 1.0, 
        "deal": 87.3, 
        "diff": -0.6, 
        "sell": 87.3
    }, 
    "110501": {
        "buy": 87.0, 
        "count": 1.0, 
        "deal": 87.3, 
        "diff": -0.6, 
        "sell": 87.3
    }, 
    "110802": {
        "buy": 87.2, 
        "count": 1.0, 
        "deal": 87.3, 
        "diff": -0.6, 
        "sell": 87.3
    }, 
    "110827": {
        "buy": 87.2, 
        "count": 1.0, 
        "deal": 87.3, 
        "diff": -0.6, 
        "sell": 87.3
    }, 
    "110832": {
        "buy": 87.2, 
        "count": 1.0, 
        "deal": 87.3, 
        "diff": -0.6, 
        "sell": 87.3
    }, 
    "110902": {
        "buy": 87.2, 
        "count": 1.0, 
        "deal": 87.4, 
        "diff": -0.5, 
        "sell": 87.4
    }, 
    "110937": {
        "buy": 87.2, 
        "count": 2.0, 
        "deal": 87.3, 
        "diff": -0.6, 
        "sell": 87.3
    }, 
    "111058": {
        "buy": 87.3, 
        "count": 1.0, 
        "deal": 87.4, 
        "diff": -0.5, 
        "sell": 87.4
    }, 
    "111138": {
        "buy": 87.3, 
        "count": 1.0, 
        "deal": 87.4, 
        "diff": -0.5, 
        "sell": 87.4
    }, 
    "111143": {
        "buy": 87.3, 
        "count": 8.0, 
        "deal": 87.4, 
        "diff": -0.5, 
        "sell": 87.4
    }, 
    "111208": {
        "buy": 87.4, 
        "count": 1.0, 
        "deal": 87.5, 
        "diff": -0.4, 
        "sell": 87.5
    }, 
    "111328": {
        "buy": 87.4, 
        "count": 1.0, 
        "deal": 87.4, 
        "diff": -0.5, 
        "sell": 87.5
    }, 
    "111359": {
        "buy": 87.4, 
        "count": 1.0, 
        "deal": 87.5, 
        "diff": -0.4, 
        "sell": 87.5
    }, 
    "111449": {
        "buy": 87.4, 
        "count": 2.0, 
        "deal": 87.5, 
        "diff": -0.4, 
        "sell": 87.5
    }, 
    "111639": {
        "buy": 87.4, 
        "count": 1.0, 
        "deal": 87.5, 
        "diff": -0.4, 
        "sell": 87.5
    }, 
    "111654": {
        "buy": 87.4, 
        "count": 1.0, 
        "deal": 87.5, 
        "diff": -0.4, 
        "sell": 87.5
    }, 
    "111745": {
        "buy": 87.4, 
        "count": 1.0, 
        "deal": 87.5, 
        "diff": -0.4, 
        "sell": 87.5
    }, 
    "111750": {
        "buy": 87.4, 
        "count": 10.0, 
        "deal": 87.5, 
        "diff": -0.4, 
        "sell": 87.5
    }, 
    "111955": {
        "buy": 87.5, 
        "count": 1.0, 
        "deal": 87.6, 
        "diff": -0.3, 
        "sell": 87.6
    }, 
    "112025": {
        "buy": 87.5, 
        "count": 5.0, 
        "deal": 87.6, 
        "diff": -0.3, 
        "sell": 87.6
    }, 
    "112035": {
        "buy": 87.5, 
        "count": 1.0, 
        "deal": 87.6, 
        "diff": -0.3, 
        "sell": 87.6
    }, 
    "112146": {
        "buy": 87.5, 
        "count": 1.0, 
        "deal": 87.6, 
        "diff": -0.3, 
        "sell": 87.6
    }, 
    "112206": {
        "buy": 87.5, 
        "count": 3.0, 
        "deal": 87.6, 
        "diff": -0.3, 
        "sell": 87.6
    }, 
    "112241": {
        "buy": 87.5, 
        "count": 2.0, 
        "deal": 87.6, 
        "diff": -0.3, 
        "sell": 87.6
    }, 
    "112251": {
        "buy": 87.5, 
        "count": 1.0, 
        "deal": 87.7, 
        "diff": -0.2, 
        "sell": 87.7
    }, 
    "112407": {
        "buy": 87.5, 
        "count": 1.0, 
        "deal": 87.7, 
        "diff": -0.2, 
        "sell": 87.7
    }, 
    "112412": {
        "buy": 87.5, 
        "count": 1.0, 
        "deal": 87.7, 
        "diff": -0.2, 
        "sell": 87.7
    }, 
    "112427": {
        "buy": 87.5, 
        "count": 5.0, 
        "deal": 87.5, 
        "diff": -0.4, 
        "sell": 87.7
    }, 
    "112547": {
        "buy": 87.4, 
        "count": 1.0, 
        "deal": 87.5, 
        "diff": -0.4, 
        "sell": 87.5
    }, 
    "112617": {
        "buy": 87.4, 
        "count": 1.0, 
        "deal": 87.6, 
        "diff": -0.3, 
        "sell": 87.6
    }, 
    "112637": {
        "buy": 87.4, 
        "count": 1.0, 
        "deal": 87.4, 
        "diff": -0.5, 
        "sell": 87.6
    }, 
    "112707": {
        "buy": 87.4, 
        "count": 1.0, 
        "deal": 87.4, 
        "diff": -0.5, 
        "sell": 87.5
    }, 
    "112727": {
        "buy": 87.4, 
        "count": 1.0, 
        "deal": 87.4, 
        "diff": -0.5, 
        "sell": 87.5
    }, 
    "112817": {
        "buy": 87.3, 
        "count": 1.0, 
        "deal": 87.3, 
        "diff": -0.6, 
        "sell": 87.4
    }, 
    "112848": {
        "buy": 87.2, 
        "count": 1.0, 
        "deal": 87.4, 
        "diff": -0.5, 
        "sell": 87.4
    }, 
    "112918": {
        "buy": 87.2, 
        "count": 1.0, 
        "deal": 87.2, 
        "diff": -0.7, 
        "sell": 87.3
    }, 
    "112938": {
        "buy": 87.1, 
        "count": 1.0, 
        "deal": 87.1, 
        "diff": -0.8, 
        "sell": 87.3
    }, 
    "113038": {
        "buy": 87.1, 
        "count": 1.0, 
        "deal": 87.1, 
        "diff": -0.8, 
        "sell": 87.2
    }, 
    "113143": {
        "buy": 87.0, 
        "count": 7.0, 
        "deal": 87.0, 
        "diff": -0.9, 
        "sell": 87.1
    }, 
    "113148": {
        "buy": 87.0, 
        "count": 1.0, 
        "deal": 87.0, 
        "diff": -0.9, 
        "sell": 87.1
    }, 
    "113158": {
        "buy": 86.8, 
        "count": 2.0, 
        "deal": 86.9, 
        "diff": -1.0, 
        "sell": 86.9
    }, 
    "113203": {
        "buy": 86.9, 
        "count": 1.0, 
        "deal": 87.0, 
        "diff": -0.9, 
        "sell": 87.1
    }, 
    "113349": {
        "buy": 87.0, 
        "count": 3.0, 
        "deal": 87.1, 
        "diff": -0.8, 
        "sell": 87.1
    }, 
    "113359": {
        "buy": 87.0, 
        "count": 3.0, 
        "deal": 87.1, 
        "diff": -0.8, 
        "sell": 87.1
    }, 
    "113445": {
        "buy": 87.1, 
        "count": 1.0, 
        "deal": 87.2, 
        "diff": -0.7, 
        "sell": 87.2
    }, 
    "113500": {
        "buy": 87.1, 
        "count": 10.0, 
        "deal": 87.2, 
        "diff": -0.7, 
        "sell": 87.2
    }, 
    "113905": {
        "buy": 87.2, 
        "count": 2.0, 
        "deal": 87.2, 
        "diff": -0.7, 
        "sell": 87.3
    }, 
    "113956": {
        "buy": 87.1, 
        "count": 1.0, 
        "deal": 87.1, 
        "diff": -0.8, 
        "sell": 87.3
    }, 
    "114016": {
        "buy": 87.1, 
        "count": 2.0, 
        "deal": 87.1, 
        "diff": -0.8, 
        "sell": 87.2
    }, 
    "114226": {
        "buy": 87.0, 
        "count": 1.0, 
        "deal": 87.1, 
        "diff": -0.8, 
        "sell": 87.1
    }, 
    "114437": {
        "buy": 87.0, 
        "count": 1.0, 
        "deal": 87.1, 
        "diff": -0.8, 
        "sell": 87.1
    }, 
    "114452": {
        "buy": 87.0, 
        "count": 1.0, 
        "deal": 87.0, 
        "diff": -0.9, 
        "sell": 87.1
    }, 
    "114853": {
        "buy": 87.0, 
        "count": 1.0, 
        "deal": 87.1, 
        "diff": -0.8, 
        "sell": 87.1
    }, 
    "114858": {
        "buy": 87.0, 
        "count": 2.0, 
        "deal": 87.1, 
        "diff": -0.8, 
        "sell": 87.1
    }, 
    "114933": {
        "buy": 87.0, 
        "count": 2.0, 
        "deal": 87.0, 
        "diff": -0.9, 
        "sell": 87.1
    }, 
    "115014": {
        "buy": 87.0, 
        "count": 1.0, 
        "deal": 87.1, 
        "diff": -0.8, 
        "sell": 87.1
    }, 
    "115109": {
        "buy": 87.0, 
        "count": 1.0, 
        "deal": 87.1, 
        "diff": -0.8, 
        "sell": 87.1
    }, 
    "115204": {
        "buy": 87.0, 
        "count": 1.0, 
        "deal": 87.1, 
        "diff": -0.8, 
        "sell": 87.1
    }, 
    "115334": {
        "buy": 87.0, 
        "count": 1.0, 
        "deal": 87.0, 
        "diff": -0.9, 
        "sell": 87.1
    }, 
    "115636": {
        "buy": 87.0, 
        "count": 1.0, 
        "deal": 87.0, 
        "diff": -0.9, 
        "sell": 87.1
    }, 
    "115641": {
        "buy": 87.0, 
        "count": 1.0, 
        "deal": 87.1, 
        "diff": -0.8, 
        "sell": 87.1
    }, 
    "115906": {
        "buy": 87.0, 
        "count": 5.0, 
        "deal": 87.1, 
        "diff": -0.8, 
        "sell": 87.1
    }, 
    "115911": {
        "buy": 87.0, 
        "count": 5.0, 
        "deal": 87.1, 
        "diff": -0.8, 
        "sell": 87.1
    }, 
    "115946": {
        "buy": 87.1, 
        "count": 1.0, 
        "deal": 87.2, 
        "diff": -0.7, 
        "sell": 87.2
    }, 
    "120222": {
        "buy": 87.1, 
        "count": 5.0, 
        "deal": 87.2, 
        "diff": -0.7, 
        "sell": 87.2
    }, 
    "120257": {
        "buy": 87.2, 
        "count": 1.0, 
        "deal": 87.2, 
        "diff": -0.7, 
        "sell": 87.3
    }, 
    "120433": {
        "buy": 87.2, 
        "count": 2.0, 
        "deal": 87.2, 
        "diff": -0.7, 
        "sell": 87.3
    }, 
    "120503": {
        "buy": 87.2, 
        "count": 1.0, 
        "deal": 87.3, 
        "diff": -0.6, 
        "sell": 87.3
    }, 
    "120548": {
        "buy": 87.2, 
        "count": 1.0, 
        "deal": 87.3, 
        "diff": -0.6, 
        "sell": 87.3
    }, 
    "120754": {
        "buy": 87.2, 
        "count": 1.0, 
        "deal": 87.3, 
        "diff": -0.6, 
        "sell": 87.3
    }, 
    "120954": {
        "buy": 87.2, 
        "count": 3.0, 
        "deal": 87.3, 
        "diff": -0.6, 
        "sell": 87.3
    }, 
    "121024": {
        "buy": 87.2, 
        "count": 1.0, 
        "deal": 87.2, 
        "diff": -0.7, 
        "sell": 87.3
    }, 
    "121125": {
        "buy": 87.2, 
        "count": 2.0, 
        "deal": 87.2, 
        "diff": -0.7, 
        "sell": 87.3
    }, 
    "121130": {
        "buy": 87.2, 
        "count": 6.0, 
        "deal": 87.2, 
        "diff": -0.7, 
        "sell": 87.3
    }, 
    "121501": {
        "buy": 87.2, 
        "count": 2.0, 
        "deal": 87.2, 
        "diff": -0.7, 
        "sell": 87.3
    }, 
    "121747": {
        "buy": 87.1, 
        "count": 1.0, 
        "deal": 87.2, 
        "diff": -0.7, 
        "sell": 87.3
    }, 
    "122107": {
        "buy": 87.1, 
        "count": 2.0, 
        "deal": 87.1, 
        "diff": -0.8, 
        "sell": 87.3
    }, 
    "122138": {
        "buy": 87.1, 
        "count": 1.0, 
        "deal": 87.1, 
        "diff": -0.8, 
        "sell": 87.3
    }, 
    "122439": {
        "buy": 87.1, 
        "count": 1.0, 
        "deal": 87.1, 
        "diff": -0.8, 
        "sell": 87.2
    }, 
    "122534": {
        "buy": 87.1, 
        "count": 2.0, 
        "deal": 87.1, 
        "diff": -0.8, 
        "sell": 87.2
    }, 
    "122639": {
        "buy": 87.1, 
        "count": 1.0, 
        "deal": 87.1, 
        "diff": -0.8, 
        "sell": 87.2
    }, 
    "122845": {
        "buy": 87.1, 
        "count": 1.0, 
        "deal": 87.1, 
        "diff": -0.8, 
        "sell": 87.2
    }, 
    "123035": {
        "buy": 87.1, 
        "count": 2.0, 
        "deal": 87.1, 
        "diff": -0.8, 
        "sell": 87.2
    }, 
    "123206": {
        "buy": 87.1, 
        "count": 1.0, 
        "deal": 87.1, 
        "diff": -0.8, 
        "sell": 87.2
    }, 
    "123306": {
        "buy": 87.1, 
        "count": 1.0, 
        "deal": 87.2, 
        "diff": -0.7, 
        "sell": 87.2
    }, 
    "123412": {
        "buy": 87.1, 
        "count": 2.0, 
        "deal": 87.2, 
        "diff": -0.7, 
        "sell": 87.2
    }, 
    "123417": {
        "buy": 87.1, 
        "count": 1.0, 
        "deal": 87.2, 
        "diff": -0.7, 
        "sell": 87.2
    }, 
    "123422": {
        "buy": 87.1, 
        "count": 1.0, 
        "deal": 87.2, 
        "diff": -0.7, 
        "sell": 87.2
    }, 
    "124023": {
        "buy": 87.1, 
        "count": 1.0, 
        "deal": 87.2, 
        "diff": -0.7, 
        "sell": 87.2
    }, 
    "124043": {
        "buy": 87.1, 
        "count": 3.0, 
        "deal": 87.1, 
        "diff": -0.8, 
        "sell": 87.2
    }, 
    "124058": {
        "buy": 87.1, 
        "count": 6.0, 
        "deal": 87.1, 
        "diff": -0.8, 
        "sell": 87.2
    }, 
    "124118": {
        "buy": 87.1, 
        "count": 1.0, 
        "deal": 87.1, 
        "diff": -0.8, 
        "sell": 87.2
    }, 
    "124128": {
        "buy": 87.1, 
        "count": 1.0, 
        "deal": 87.1, 
        "diff": -0.8, 
        "sell": 87.2
    }, 
    "124148": {
        "buy": 87.0, 
        "count": 4.0, 
        "deal": 87.1, 
        "diff": -0.8, 
        "sell": 87.1
    }, 
    "124419": {
        "buy": 87.1, 
        "count": 1.0, 
        "deal": 87.1, 
        "diff": -0.8, 
        "sell": 87.2
    }, 
    "124444": {
        "buy": 87.1, 
        "count": 3.0, 
        "deal": 87.1, 
        "diff": -0.8, 
        "sell": 87.2
    }, 
    "124454": {
        "buy": 87.1, 
        "count": 1.0, 
        "deal": 87.1, 
        "diff": -0.8, 
        "sell": 87.2
    }, 
    "124555": {
        "buy": 87.1, 
        "count": 2.0, 
        "deal": 87.1, 
        "diff": -0.8, 
        "sell": 87.2
    }, 
    "124705": {
        "buy": 87.1, 
        "count": 5.0, 
        "deal": 87.1, 
        "diff": -0.8, 
        "sell": 87.2
    }, 
    "124740": {
        "buy": 87.1, 
        "count": 1.0, 
        "deal": 87.1, 
        "diff": -0.8, 
        "sell": 87.2
    }, 
    "124830": {
        "buy": 87.1, 
        "count": 4.0, 
        "deal": 87.0, 
        "diff": -0.9, 
        "sell": 87.2
    }, 
    "124925": {
        "buy": 87.1, 
        "count": 1.0, 
        "deal": 87.1, 
        "diff": -0.8, 
        "sell": 87.2
    }, 
    "125005": {
        "buy": 87.1, 
        "count": 1.0, 
        "deal": 87.2, 
        "diff": -0.7, 
        "sell": 87.2
    }, 
    "125046": {
        "buy": 87.1, 
        "count": 11.0, 
        "deal": 87.2, 
        "diff": -0.7, 
        "sell": 87.2
    }, 
    "125101": {
        "buy": 87.1, 
        "count": 2.0, 
        "deal": 87.2, 
        "diff": -0.7, 
        "sell": 87.2
    }, 
    "125201": {
        "buy": 87.1, 
        "count": 1.0, 
        "deal": 87.2, 
        "diff": -0.7, 
        "sell": 87.2
    }, 
    "125221": {
        "buy": 87.1, 
        "count": 3.0, 
        "deal": 87.1, 
        "diff": -0.8, 
        "sell": 87.3
    }, 
    "125301": {
        "buy": 87.2, 
        "count": 2.0, 
        "deal": 87.3, 
        "diff": -0.6, 
        "sell": 87.3
    }, 
    "125331": {
        "buy": 87.2, 
        "count": 1.0, 
        "deal": 87.2, 
        "diff": -0.7, 
        "sell": 87.3
    }, 
    "125457": {
        "buy": 87.2, 
        "count": 1.0, 
        "deal": 87.3, 
        "diff": -0.6, 
        "sell": 87.3
    }, 
    "125502": {
        "buy": 87.2, 
        "count": 1.0, 
        "deal": 87.2, 
        "diff": -0.7, 
        "sell": 87.3
    }, 
    "125557": {
        "buy": 87.2, 
        "count": 1.0, 
        "deal": 87.2, 
        "diff": -0.7, 
        "sell": 87.3
    }, 
    "125637": {
        "buy": 87.2, 
        "count": 2.0, 
        "deal": 87.2, 
        "diff": -0.7, 
        "sell": 87.3
    }, 
    "125738": {
        "buy": 87.2, 
        "count": 1.0, 
        "deal": 87.2, 
        "diff": -0.7, 
        "sell": 87.3
    }, 
    "125813": {
        "buy": 87.2, 
        "count": 1.0, 
        "deal": 87.2, 
        "diff": -0.7, 
        "sell": 87.3
    }, 
    "125818": {
        "buy": 87.2, 
        "count": 1.0, 
        "deal": 87.2, 
        "diff": -0.7, 
        "sell": 87.3
    }, 
    "125853": {
        "buy": 87.2, 
        "count": 2.0, 
        "deal": 87.2, 
        "diff": -0.7, 
        "sell": 87.3
    }, 
    "125858": {
        "buy": 87.1, 
        "count": 1.0, 
        "deal": 87.1, 
        "diff": -0.8, 
        "sell": 87.3
    }, 
    "125918": {
        "buy": 87.1, 
        "count": 1.0, 
        "deal": 87.1, 
        "diff": -0.8, 
        "sell": 87.2
    }, 
    "130003": {
        "buy": 87.1, 
        "count": 1.0, 
        "deal": 87.1, 
        "diff": -0.8, 
        "sell": 87.2
    }, 
    "130028": {
        "buy": 87.1, 
        "count": 6.0, 
        "deal": 87.1, 
        "diff": -0.8, 
        "sell": 87.2
    }, 
    "130033": {
        "buy": 87.1, 
        "count": 3.0, 
        "deal": 87.1, 
        "diff": -0.8, 
        "sell": 87.2
    }, 
    "130043": {
        "buy": 87.1, 
        "count": 1.0, 
        "deal": 87.1, 
        "diff": -0.8, 
        "sell": 87.2
    }, 
    "130048": {
        "buy": 87.1, 
        "count": 10.0, 
        "deal": 87.1, 
        "diff": -0.8, 
        "sell": 87.2
    }, 
    "130129": {
        "buy": 87.1, 
        "count": 1.0, 
        "deal": 87.2, 
        "diff": -0.7, 
        "sell": 87.2
    }, 
    "130239": {
        "buy": 87.1, 
        "count": 2.0, 
        "deal": 87.1, 
        "diff": -0.8, 
        "sell": 87.2
    }, 
    "130319": {
        "buy": 87.1, 
        "count": 1.0, 
        "deal": 87.1, 
        "diff": -0.8, 
        "sell": 87.2
    }, 
    "130324": {
        "buy": 87.1, 
        "count": 1.0, 
        "deal": 87.1, 
        "diff": -0.8, 
        "sell": 87.2
    }, 
    "130405": {
        "buy": 87.1, 
        "count": 1.0, 
        "deal": 87.1, 
        "diff": -0.8, 
        "sell": 87.2
    }, 
    "130445": {
        "buy": 87.1, 
        "count": 1.0, 
        "deal": 87.1, 
        "diff": -0.8, 
        "sell": 87.2
    }, 
    "130520": {
        "buy": 87.1, 
        "count": 2.0, 
        "deal": 87.2, 
        "diff": -0.7, 
        "sell": 87.2
    }, 
    "130530": {
        "buy": 87.1, 
        "count": 1.0, 
        "deal": 87.2, 
        "diff": -0.7, 
        "sell": 87.2
    }, 
    "130610": {
        "buy": 87.1, 
        "count": 5.0, 
        "deal": 87.1, 
        "diff": -0.8, 
        "sell": 87.2
    }, 
    "130615": {
        "buy": 87.0, 
        "count": 1.0, 
        "deal": 87.2, 
        "diff": -0.7, 
        "sell": 87.2
    }, 
    "130645": {
        "buy": 87.2, 
        "count": 1.0, 
        "deal": 87.2, 
        "diff": -0.7, 
        "sell": 87.3
    }, 
    "130720": {
        "buy": 87.0, 
        "count": 1.0, 
        "deal": 87.1, 
        "diff": -0.8, 
        "sell": 87.2
    }, 
    "130730": {
        "buy": 87.1, 
        "count": 1.0, 
        "deal": 87.1, 
        "diff": -0.8, 
        "sell": 87.2
    }, 
    "130750": {
        "buy": 87.1, 
        "count": 1.0, 
        "deal": 87.1, 
        "diff": -0.8, 
        "sell": 87.2
    }, 
    "130825": {
        "buy": 87.1, 
        "count": 1.0, 
        "deal": 87.1, 
        "diff": -0.8, 
        "sell": 87.2
    }, 
    "130856": {
        "buy": 87.1, 
        "count": 1.0, 
        "deal": 87.1, 
        "diff": -0.8, 
        "sell": 87.2
    }, 
    "130906": {
        "buy": 87.1, 
        "count": 1.0, 
        "deal": 87.2, 
        "diff": -0.7, 
        "sell": 87.2
    }, 
    "131046": {
        "buy": 87.1, 
        "count": 1.0, 
        "deal": 87.1, 
        "diff": -0.8, 
        "sell": 87.2
    }, 
    "131056": {
        "buy": 87.1, 
        "count": 5.0, 
        "deal": 87.1, 
        "diff": -0.8, 
        "sell": 87.2
    }, 
    "131121": {
        "buy": 87.1, 
        "count": 1.0, 
        "deal": 87.2, 
        "diff": -0.7, 
        "sell": 87.2
    }, 
    "131126": {
        "buy": 87.1, 
        "count": 1.0, 
        "deal": 87.1, 
        "diff": -0.8, 
        "sell": 87.2
    }, 
    "131156": {
        "buy": 87.1, 
        "count": 1.0, 
        "deal": 87.1, 
        "diff": -0.8, 
        "sell": 87.2
    }, 
    "131236": {
        "buy": 87.1, 
        "count": 1.0, 
        "deal": 87.1, 
        "diff": -0.8, 
        "sell": 87.2
    }, 
    "131317": {
        "buy": 87.1, 
        "count": 1.0, 
        "deal": 87.1, 
        "diff": -0.8, 
        "sell": 87.2
    }, 
    "131347": {
        "buy": 87.0, 
        "count": 1.0, 
        "deal": 87.1, 
        "diff": -0.8, 
        "sell": 87.1
    }, 
    "131352": {
        "buy": 87.1, 
        "count": 1.0, 
        "deal": 87.1, 
        "diff": -0.8, 
        "sell": 87.2
    }, 
    "131402": {
        "buy": 87.0, 
        "count": 1.0, 
        "deal": 87.0, 
        "diff": -0.9, 
        "sell": 87.2
    }, 
    "131443": {
        "buy": 87.0, 
        "count": 2.0, 
        "deal": 87.0, 
        "diff": -0.9, 
        "sell": 87.2
    }, 
    "131503": {
        "buy": 87.0, 
        "count": 1.0, 
        "deal": 87.0, 
        "diff": -0.9, 
        "sell": 87.2
    }, 
    "131533": {
        "buy": 87.0, 
        "count": 1.0, 
        "deal": 87.0, 
        "diff": -0.9, 
        "sell": 87.1
    }, 
    "131553": {
        "buy": 87.0, 
        "count": 1.0, 
        "deal": 87.0, 
        "diff": -0.9, 
        "sell": 87.1
    }, 
    "131603": {
        "buy": 87.0, 
        "count": 1.0, 
        "deal": 87.1, 
        "diff": -0.8, 
        "sell": 87.1
    }, 
    "131608": {
        "buy": 87.0, 
        "count": 1.0, 
        "deal": 87.2, 
        "diff": -0.7, 
        "sell": 87.2
    }, 
    "131618": {
        "buy": 87.1, 
        "count": 1.0, 
        "deal": 87.1, 
        "diff": -0.8, 
        "sell": 87.2
    }, 
    "131638": {
        "buy": 87.0, 
        "count": 2.0, 
        "deal": 87.0, 
        "diff": -0.9, 
        "sell": 87.1
    }, 
    "131643": {
        "buy": 87.0, 
        "count": 1.0, 
        "deal": 87.0, 
        "diff": -0.9, 
        "sell": 87.1
    }, 
    "131703": {
        "buy": 87.0, 
        "count": 3.0, 
        "deal": 87.1, 
        "diff": -0.8, 
        "sell": 87.1
    }, 
    "131743": {
        "buy": 87.0, 
        "count": 2.0, 
        "deal": 87.1, 
        "diff": -0.8, 
        "sell": 87.1
    }, 
    "131748": {
        "buy": 87.0, 
        "count": 1.0, 
        "deal": 87.1, 
        "diff": -0.8, 
        "sell": 87.2
    }, 
    "131858": {
        "buy": 87.0, 
        "count": 1.0, 
        "deal": 87.0, 
        "diff": -0.9, 
        "sell": 87.1
    }, 
    "131908": {
        "buy": 87.0, 
        "count": 2.0, 
        "deal": 87.1, 
        "diff": -0.8, 
        "sell": 87.1
    }, 
    "131929": {
        "buy": 87.0, 
        "count": 2.0, 
        "deal": 87.1, 
        "diff": -0.8, 
        "sell": 87.1
    }, 
    "132004": {
        "buy": 87.0, 
        "count": 3.0, 
        "deal": 87.1, 
        "diff": -0.8, 
        "sell": 87.1
    }, 
    "132009": {
        "buy": 87.0, 
        "count": 1.0, 
        "deal": 87.1, 
        "diff": -0.8, 
        "sell": 87.1
    }, 
    "132029": {
        "buy": 87.0, 
        "count": 10.0, 
        "deal": 87.1, 
        "diff": -0.8, 
        "sell": 87.1
    }, 
    "132104": {
        "buy": 87.1, 
        "count": 10.0, 
        "deal": 87.2, 
        "diff": -0.7, 
        "sell": 87.2
    }, 
    "132109": {
        "buy": 87.1, 
        "count": 2.0, 
        "deal": 87.1, 
        "diff": -0.8, 
        "sell": 87.2
    }, 
    "132129": {
        "buy": 87.1, 
        "count": 1.0, 
        "deal": 87.1, 
        "diff": -0.8, 
        "sell": 87.2
    }, 
    "132149": {
        "buy": 87.1, 
        "count": 2.0, 
        "deal": 87.1, 
        "diff": -0.8, 
        "sell": 87.2
    }, 
    "132154": {
        "buy": 87.1, 
        "count": 1.0, 
        "deal": 87.1, 
        "diff": -0.8, 
        "sell": 87.2
    }, 
    "132159": {
        "buy": 87.0, 
        "count": 1.0, 
        "deal": 87.2, 
        "diff": -0.7, 
        "sell": 87.2
    }, 
    "132204": {
        "buy": 87.0, 
        "count": 3.0, 
        "deal": 87.2, 
        "diff": -0.7, 
        "sell": 87.2
    }, 
    "132209": {
        "buy": 87.0, 
        "count": 3.0, 
        "deal": 87.0, 
        "diff": -0.9, 
        "sell": 87.3
    }, 
    "132229": {
        "buy": 87.1, 
        "count": 1.0, 
        "deal": 87.0, 
        "diff": -0.9, 
        "sell": 87.2
    }, 
    "132249": {
        "buy": 87.0, 
        "count": 11.0, 
        "deal": 87.0, 
        "diff": -0.9, 
        "sell": 87.1
    }, 
    "132304": {
        "buy": 87.0, 
        "count": 1.0, 
        "deal": 87.0, 
        "diff": -0.9, 
        "sell": 87.1
    }, 
    "132319": {
        "buy": 87.0, 
        "count": 6.0, 
        "deal": 87.0, 
        "diff": -0.9, 
        "sell": 87.1
    }, 
    "132324": {
        "buy": 87.0, 
        "count": 1.0, 
        "deal": 87.0, 
        "diff": -0.9, 
        "sell": 87.1
    }, 
    "132340": {
        "buy": 87.0, 
        "count": 1.0, 
        "deal": 87.0, 
        "diff": -0.9, 
        "sell": 87.1
    }, 
    "132350": {
        "buy": 87.0, 
        "count": 1.0, 
        "deal": 87.1, 
        "diff": -0.8, 
        "sell": 87.1
    }, 
    "132355": {
        "buy": 87.0, 
        "count": 4.0, 
        "deal": 87.0, 
        "diff": -0.9, 
        "sell": 87.1
    }, 
    "132405": {
        "buy": 87.0, 
        "count": 1.0, 
        "deal": 87.0, 
        "diff": -0.9, 
        "sell": 87.1
    }, 
    "132415": {
        "buy": 87.0, 
        "count": 1.0, 
        "deal": 87.1, 
        "diff": -0.8, 
        "sell": 87.1
    }, 
    "132426": {
        "buy": 87.0, 
        "count": 2.0, 
        "deal": 87.1, 
        "diff": -0.8, 
        "sell": 87.1
    }, 
    "132431": {
        "buy": 87.0, 
        "count": 2.0, 
        "deal": 87.0, 
        "diff": -0.9, 
        "sell": 87.1
    }, 
    "132446": {
        "buy": 87.0, 
        "count": 1.0, 
        "deal": 87.0, 
        "diff": -0.9, 
        "sell": 87.1
    }, 
    "133000": {
        "buy": 86.9, 
        "count": 94.0, 
        "deal": 87.0, 
        "diff": -0.9, 
        "sell": 87.0
    }, 
    "143000": {
        "buy": 86.9, 
        "count": 3.0, 
        "deal": 87.0, 
        "diff": -0.9, 
        "sell": 87.0
    }
}