{
    "090018": {
        "buy": 89.8, 
        "count": 1.0, 
        "deal": 89.9, 
        "diff": -0.1, 
        "sell": 89.9
    }, 
    "090028": {
        "buy": 89.8, 
        "count": 4.0, 
        "deal": 89.9, 
        "diff": -0.1, 
        "sell": 89.9
    }, 
    "090033": {
        "buy": 89.8, 
        "count": 1.0, 
        "deal": 89.9, 
        "diff": -0.1, 
        "sell": 89.9
    }, 
    "090043": {
        "buy": 89.8, 
        "count": 1.0, 
        "deal": 89.8, 
        "diff": -0.2, 
        "sell": 89.9
    }, 
    "090054": {
        "buy": 89.7, 
        "count": 1.0, 
        "deal": 89.9, 
        "diff": -0.1, 
        "sell": 89.9
    }, 
    "090434": {
        "buy": 89.7, 
        "count": 2.0, 
        "deal": 89.7, 
        "diff": -0.3, 
        "sell": 89.9
    }, 
    "090454": {
        "buy": 89.5, 
        "count": 1.0, 
        "deal": 89.5, 
        "diff": -0.5, 
        "sell": 89.7
    }, 
    "090459": {
        "buy": 89.5, 
        "count": 3.0, 
        "deal": 89.5, 
        "diff": -0.5, 
        "sell": 89.7
    }, 
    "090510": {
        "buy": 89.3, 
        "count": 3.0, 
        "deal": 89.5, 
        "diff": -0.5, 
        "sell": 89.5
    }, 
    "090625": {
        "buy": 89.3, 
        "count": 1.0, 
        "deal": 89.3, 
        "diff": -0.7, 
        "sell": 89.5
    }, 
    "090655": {
        "buy": 89.3, 
        "count": 2.0, 
        "deal": 89.3, 
        "diff": -0.7, 
        "sell": 89.5
    }, 
    "090701": {
        "buy": 89.2, 
        "count": 7.0, 
        "deal": 89.3, 
        "diff": -0.7, 
        "sell": 89.3
    }, 
    "090706": {
        "buy": 89.2, 
        "count": 1.0, 
        "deal": 89.3, 
        "diff": -0.7, 
        "sell": 89.3
    }, 
    "090956": {
        "buy": 89.3, 
        "count": 1.0, 
        "deal": 89.3, 
        "diff": -0.7, 
        "sell": 89.7
    }, 
    "091001": {
        "buy": 89.3, 
        "count": 1.0, 
        "deal": 89.3, 
        "diff": -0.7, 
        "sell": 89.7
    }, 
    "091041": {
        "buy": 89.3, 
        "count": 2.0, 
        "deal": 89.3, 
        "diff": -0.7, 
        "sell": 89.7
    }, 
    "091111": {
        "buy": 89.3, 
        "count": 1.0, 
        "deal": 89.3, 
        "diff": -0.7, 
        "sell": 89.5
    }, 
    "092245": {
        "buy": 89.2, 
        "count": 1.0, 
        "deal": 89.2, 
        "diff": -0.8, 
        "sell": 89.4
    }, 
    "092300": {
        "buy": 89.1, 
        "count": 3.0, 
        "deal": 89.1, 
        "diff": -0.9, 
        "sell": 89.2
    }, 
    "092305": {
        "buy": 89.0, 
        "count": 7.0, 
        "deal": 89.0, 
        "diff": -1.0, 
        "sell": 89.1
    }, 
    "092310": {
        "buy": 88.9, 
        "count": 1.0, 
        "deal": 88.9, 
        "diff": -1.1, 
        "sell": 89.0
    }, 
    "092315": {
        "buy": 88.9, 
        "count": 3.0, 
        "deal": 88.9, 
        "diff": -1.1, 
        "sell": 89.0
    }, 
    "092320": {
        "buy": 88.8, 
        "count": 2.0, 
        "deal": 88.8, 
        "diff": -1.2, 
        "sell": 88.9
    }, 
    "092325": {
        "buy": 88.7, 
        "count": 3.0, 
        "deal": 88.6, 
        "diff": -1.4, 
        "sell": 88.8
    }, 
    "092335": {
        "buy": 88.6, 
        "count": 2.0, 
        "deal": 88.6, 
        "diff": -1.4, 
        "sell": 88.7
    }, 
    "092340": {
        "buy": 88.6, 
        "count": 4.0, 
        "deal": 88.5, 
        "diff": -1.5, 
        "sell": 88.7
    }, 
    "092345": {
        "buy": 88.5, 
        "count": 5.0, 
        "deal": 88.5, 
        "diff": -1.5, 
        "sell": 88.7
    }, 
    "092350": {
        "buy": 88.3, 
        "count": 4.0, 
        "deal": 88.2, 
        "diff": -1.8, 
        "sell": 88.7
    }, 
    "092355": {
        "buy": 88.2, 
        "count": 10.0, 
        "deal": 88.2, 
        "diff": -1.8, 
        "sell": 88.7
    }, 
    "092400": {
        "buy": 88.1, 
        "count": 4.0, 
        "deal": 88.0, 
        "diff": -2.0, 
        "sell": 88.7
    }, 
    "092410": {
        "buy": 88.0, 
        "count": 3.0, 
        "deal": 88.0, 
        "diff": -2.0, 
        "sell": 88.5
    }, 
    "092415": {
        "buy": 88.0, 
        "count": 12.0, 
        "deal": 88.0, 
        "diff": -2.0, 
        "sell": 88.5
    }, 
    "092420": {
        "buy": 87.8, 
        "count": 5.0, 
        "deal": 88.0, 
        "diff": -2.0, 
        "sell": 88.0
    }, 
    "092425": {
        "buy": 87.8, 
        "count": 1.0, 
        "deal": 88.0, 
        "diff": -2.0, 
        "sell": 88.0
    }, 
    "092430": {
        "buy": 88.0, 
        "count": 2.0, 
        "deal": 88.2, 
        "diff": -1.8, 
        "sell": 88.2
    }, 
    "092440": {
        "buy": 88.0, 
        "count": 4.0, 
        "deal": 88.2, 
        "diff": -1.8, 
        "sell": 88.2
    }, 
    "092445": {
        "buy": 88.0, 
        "count": 1.0, 
        "deal": 88.2, 
        "diff": -1.8, 
        "sell": 88.2
    }, 
    "092450": {
        "buy": 88.0, 
        "count": 3.0, 
        "deal": 88.0, 
        "diff": -2.0, 
        "sell": 88.5
    }, 
    "092455": {
        "buy": 88.0, 
        "count": 2.0, 
        "deal": 88.0, 
        "diff": -2.0, 
        "sell": 88.5
    }, 
    "092500": {
        "buy": 87.8, 
        "count": 3.0, 
        "deal": 87.8, 
        "diff": -2.2, 
        "sell": 88.5
    }, 
    "092505": {
        "buy": 87.8, 
        "count": 1.0, 
        "deal": 87.8, 
        "diff": -2.2, 
        "sell": 88.5
    }, 
    "092510": {
        "buy": 87.8, 
        "count": 3.0, 
        "deal": 87.7, 
        "diff": -2.3, 
        "sell": 88.0
    }, 
    "092515": {
        "buy": 87.7, 
        "count": 1.0, 
        "deal": 88.0, 
        "diff": -2.0, 
        "sell": 88.0
    }, 
    "092520": {
        "buy": 87.7, 
        "count": 3.0, 
        "deal": 87.7, 
        "diff": -2.3, 
        "sell": 88.5
    }, 
    "092530": {
        "buy": 87.7, 
        "count": 2.0, 
        "deal": 87.8, 
        "diff": -2.2, 
        "sell": 88.4
    }, 
    "092541": {
        "buy": 88.3, 
        "count": 2.0, 
        "deal": 87.8, 
        "diff": -2.2, 
        "sell": 88.4
    }, 
    "092616": {
        "buy": 88.0, 
        "count": 1.0, 
        "deal": 88.0, 
        "diff": -2.0, 
        "sell": 88.4
    }, 
    "092631": {
        "buy": 88.0, 
        "count": 1.0, 
        "deal": 88.4, 
        "diff": -1.6, 
        "sell": 88.4
    }, 
    "092646": {
        "buy": 88.0, 
        "count": 1.0, 
        "deal": 88.4, 
        "diff": -1.6, 
        "sell": 88.4
    }, 
    "092721": {
        "buy": 88.1, 
        "count": 1.0, 
        "deal": 88.4, 
        "diff": -1.6, 
        "sell": 88.4
    }, 
    "092726": {
        "buy": 88.1, 
        "count": 1.0, 
        "deal": 88.2, 
        "diff": -1.8, 
        "sell": 88.4
    }, 
    "092801": {
        "buy": 88.4, 
        "count": 3.0, 
        "deal": 88.5, 
        "diff": -1.5, 
        "sell": 88.5
    }, 
    "092806": {
        "buy": 88.4, 
        "count": 2.0, 
        "deal": 88.6, 
        "diff": -1.4, 
        "sell": 88.7
    }, 
    "092821": {
        "buy": 88.6, 
        "count": 1.0, 
        "deal": 88.6, 
        "diff": -1.4, 
        "sell": 88.7
    }, 
    "092841": {
        "buy": 88.4, 
        "count": 1.0, 
        "deal": 88.7, 
        "diff": -1.3, 
        "sell": 88.7
    }, 
    "093022": {
        "buy": 88.5, 
        "count": 1.0, 
        "deal": 88.7, 
        "diff": -1.3, 
        "sell": 88.7
    }, 
    "093032": {
        "buy": 88.6, 
        "count": 1.0, 
        "deal": 88.6, 
        "diff": -1.4, 
        "sell": 88.7
    }, 
    "093042": {
        "buy": 88.6, 
        "count": 1.0, 
        "deal": 88.6, 
        "diff": -1.4, 
        "sell": 88.7
    }, 
    "093102": {
        "buy": 88.5, 
        "count": 1.0, 
        "deal": 88.5, 
        "diff": -1.5, 
        "sell": 88.6
    }, 
    "093107": {
        "buy": 88.5, 
        "count": 2.0, 
        "deal": 88.5, 
        "diff": -1.5, 
        "sell": 88.6
    }, 
    "093222": {
        "buy": 88.4, 
        "count": 2.0, 
        "deal": 88.5, 
        "diff": -1.5, 
        "sell": 88.5
    }, 
    "093433": {
        "buy": 88.5, 
        "count": 3.0, 
        "deal": 88.5, 
        "diff": -1.5, 
        "sell": 88.6
    }, 
    "093734": {
        "buy": 88.4, 
        "count": 1.0, 
        "deal": 88.5, 
        "diff": -1.5, 
        "sell": 88.5
    }, 
    "093849": {
        "buy": 88.4, 
        "count": 2.0, 
        "deal": 88.5, 
        "diff": -1.5, 
        "sell": 88.5
    }, 
    "093854": {
        "buy": 88.4, 
        "count": 1.0, 
        "deal": 88.4, 
        "diff": -1.6, 
        "sell": 88.6
    }, 
    "093859": {
        "buy": 88.4, 
        "count": 2.0, 
        "deal": 88.4, 
        "diff": -1.6, 
        "sell": 88.6
    }, 
    "094024": {
        "buy": 88.3, 
        "count": 1.0, 
        "deal": 88.4, 
        "diff": -1.6, 
        "sell": 88.4
    }, 
    "094130": {
        "buy": 88.4, 
        "count": 3.0, 
        "deal": 88.3, 
        "diff": -1.7, 
        "sell": 88.6
    }, 
    "094135": {
        "buy": 88.3, 
        "count": 1.0, 
        "deal": 88.5, 
        "diff": -1.5, 
        "sell": 88.6
    }, 
    "094150": {
        "buy": 88.4, 
        "count": 1.0, 
        "deal": 88.5, 
        "diff": -1.5, 
        "sell": 88.6
    }, 
    "094521": {
        "buy": 88.3, 
        "count": 2.0, 
        "deal": 88.3, 
        "diff": -1.7, 
        "sell": 88.5
    }, 
    "094526": {
        "buy": 88.2, 
        "count": 7.0, 
        "deal": 88.2, 
        "diff": -1.8, 
        "sell": 88.3
    }, 
    "094531": {
        "buy": 88.1, 
        "count": 2.0, 
        "deal": 88.1, 
        "diff": -1.9, 
        "sell": 88.2
    }, 
    "094536": {
        "buy": 88.1, 
        "count": 5.0, 
        "deal": 88.1, 
        "diff": -1.9, 
        "sell": 88.2
    }, 
    "094557": {
        "buy": 88.0, 
        "count": 1.0, 
        "deal": 88.0, 
        "diff": -2.0, 
        "sell": 88.1
    }, 
    "094617": {
        "buy": 88.0, 
        "count": 37.0, 
        "deal": 88.0, 
        "diff": -2.0, 
        "sell": 88.1
    }, 
    "094622": {
        "buy": 87.9, 
        "count": 2.0, 
        "deal": 87.9, 
        "diff": -2.1, 
        "sell": 88.0
    }, 
    "094627": {
        "buy": 87.9, 
        "count": 1.0, 
        "deal": 87.9, 
        "diff": -2.1, 
        "sell": 88.0
    }, 
    "094642": {
        "buy": 87.8, 
        "count": 7.0, 
        "deal": 87.8, 
        "diff": -2.2, 
        "sell": 87.9
    }, 
    "094647": {
        "buy": 87.8, 
        "count": 4.0, 
        "deal": 87.8, 
        "diff": -2.2, 
        "sell": 87.9
    }, 
    "094702": {
        "buy": 87.7, 
        "count": 4.0, 
        "deal": 87.7, 
        "diff": -2.3, 
        "sell": 87.9
    }, 
    "094717": {
        "buy": 87.7, 
        "count": 1.0, 
        "deal": 87.7, 
        "diff": -2.3, 
        "sell": 87.8
    }, 
    "094757": {
        "buy": 87.7, 
        "count": 1.0, 
        "deal": 87.8, 
        "diff": -2.2, 
        "sell": 87.8
    }, 
    "094807": {
        "buy": 87.7, 
        "count": 1.0, 
        "deal": 87.9, 
        "diff": -2.1, 
        "sell": 87.9
    }, 
    "094832": {
        "buy": 87.7, 
        "count": 1.0, 
        "deal": 87.9, 
        "diff": -2.1, 
        "sell": 87.9
    }, 
    "094947": {
        "buy": 87.7, 
        "count": 1.0, 
        "deal": 87.9, 
        "diff": -2.1, 
        "sell": 87.9
    }, 
    "095032": {
        "buy": 87.9, 
        "count": 1.0, 
        "deal": 88.0, 
        "diff": -2.0, 
        "sell": 88.0
    }, 
    "095047": {
        "buy": 87.9, 
        "count": 2.0, 
        "deal": 88.0, 
        "diff": -2.0, 
        "sell": 88.0
    }, 
    "095102": {
        "buy": 87.9, 
        "count": 2.0, 
        "deal": 88.1, 
        "diff": -1.9, 
        "sell": 88.1
    }, 
    "095148": {
        "buy": 87.9, 
        "count": 1.0, 
        "deal": 88.1, 
        "diff": -1.9, 
        "sell": 88.1
    }, 
    "095223": {
        "buy": 88.0, 
        "count": 1.0, 
        "deal": 88.1, 
        "diff": -1.9, 
        "sell": 88.1
    }, 
    "095243": {
        "buy": 88.1, 
        "count": 1.0, 
        "deal": 88.2, 
        "diff": -1.8, 
        "sell": 88.2
    }, 
    "095308": {
        "buy": 88.1, 
        "count": 1.0, 
        "deal": 88.2, 
        "diff": -1.8, 
        "sell": 88.2
    }, 
    "095318": {
        "buy": 88.1, 
        "count": 1.0, 
        "deal": 88.2, 
        "diff": -1.8, 
        "sell": 88.2
    }, 
    "095413": {
        "buy": 88.1, 
        "count": 5.0, 
        "deal": 88.3, 
        "diff": -1.7, 
        "sell": 88.2
    }, 
    "095418": {
        "buy": 88.1, 
        "count": 2.0, 
        "deal": 88.3, 
        "diff": -1.7, 
        "sell": 88.3
    }, 
    "095614": {
        "buy": 88.3, 
        "count": 1.0, 
        "deal": 88.3, 
        "diff": -1.7, 
        "sell": 88.5
    }, 
    "095729": {
        "buy": 88.3, 
        "count": 1.0, 
        "deal": 88.3, 
        "diff": -1.7, 
        "sell": 88.5
    }, 
    "095734": {
        "buy": 88.3, 
        "count": 1.0, 
        "deal": 88.5, 
        "diff": -1.5, 
        "sell": 88.5
    }, 
    "095739": {
        "buy": 88.3, 
        "count": 1.0, 
        "deal": 88.3, 
        "diff": -1.7, 
        "sell": 88.5
    }, 
    "095840": {
        "buy": 88.3, 
        "count": 1.0, 
        "deal": 88.5, 
        "diff": -1.5, 
        "sell": 88.5
    }, 
    "095940": {
        "buy": 88.3, 
        "count": 1.0, 
        "deal": 88.5, 
        "diff": -1.5, 
        "sell": 88.5
    }, 
    "100025": {
        "buy": 88.3, 
        "count": 1.0, 
        "deal": 88.4, 
        "diff": -1.6, 
        "sell": 88.7
    }, 
    "100040": {
        "buy": 88.4, 
        "count": 1.0, 
        "deal": 88.4, 
        "diff": -1.6, 
        "sell": 88.6
    }, 
    "100045": {
        "buy": 88.3, 
        "count": 7.0, 
        "deal": 88.3, 
        "diff": -1.7, 
        "sell": 88.4
    }, 
    "100050": {
        "buy": 88.2, 
        "count": 1.0, 
        "deal": 88.2, 
        "diff": -1.8, 
        "sell": 88.4
    }, 
    "100125": {
        "buy": 88.3, 
        "count": 3.0, 
        "deal": 88.3, 
        "diff": -1.7, 
        "sell": 88.7
    }, 
    "100150": {
        "buy": 88.2, 
        "count": 1.0, 
        "deal": 88.3, 
        "diff": -1.7, 
        "sell": 88.3
    }, 
    "100155": {
        "buy": 88.2, 
        "count": 1.0, 
        "deal": 88.3, 
        "diff": -1.7, 
        "sell": 88.3
    }, 
    "100205": {
        "buy": 88.2, 
        "count": 4.0, 
        "deal": 88.3, 
        "diff": -1.7, 
        "sell": 88.3
    }, 
    "100431": {
        "buy": 88.3, 
        "count": 1.0, 
        "deal": 88.3, 
        "diff": -1.7, 
        "sell": 88.6
    }, 
    "100842": {
        "buy": 88.3, 
        "count": 1.0, 
        "deal": 88.3, 
        "diff": -1.7, 
        "sell": 88.5
    }, 
    "101208": {
        "buy": 88.4, 
        "count": 1.0, 
        "deal": 88.5, 
        "diff": -1.5, 
        "sell": 88.5
    }, 
    "101213": {
        "buy": 88.5, 
        "count": 8.0, 
        "deal": 88.4, 
        "diff": -1.6, 
        "sell": 88.6
    }, 
    "101253": {
        "buy": 88.3, 
        "count": 1.0, 
        "deal": 88.3, 
        "diff": -1.7, 
        "sell": 88.4
    }, 
    "101645": {
        "buy": 88.3, 
        "count": 5.0, 
        "deal": 88.3, 
        "diff": -1.7, 
        "sell": 88.4
    }, 
    "101650": {
        "buy": 88.2, 
        "count": 1.0, 
        "deal": 88.4, 
        "diff": -1.6, 
        "sell": 88.4
    }, 
    "101705": {
        "buy": 88.2, 
        "count": 1.0, 
        "deal": 88.2, 
        "diff": -1.8, 
        "sell": 88.4
    }, 
    "101740": {
        "buy": 88.1, 
        "count": 1.0, 
        "deal": 88.1, 
        "diff": -1.9, 
        "sell": 88.4
    }, 
    "102100": {
        "buy": 88.1, 
        "count": 1.0, 
        "deal": 88.1, 
        "diff": -1.9, 
        "sell": 88.4
    }, 
    "102116": {
        "buy": 88.1, 
        "count": 1.0, 
        "deal": 88.1, 
        "diff": -1.9, 
        "sell": 88.4
    }, 
    "102236": {
        "buy": 88.2, 
        "count": 1.0, 
        "deal": 88.2, 
        "diff": -1.8, 
        "sell": 88.4
    }, 
    "102522": {
        "buy": 88.2, 
        "count": 1.0, 
        "deal": 88.2, 
        "diff": -1.8, 
        "sell": 88.4
    }, 
    "102828": {
        "buy": 88.3, 
        "count": 2.0, 
        "deal": 88.4, 
        "diff": -1.6, 
        "sell": 88.4
    }, 
    "102838": {
        "buy": 88.3, 
        "count": 3.0, 
        "deal": 88.3, 
        "diff": -1.7, 
        "sell": 88.5
    }, 
    "102933": {
        "buy": 88.2, 
        "count": 1.0, 
        "deal": 88.2, 
        "diff": -1.8, 
        "sell": 88.3
    }, 
    "102938": {
        "buy": 88.2, 
        "count": 1.0, 
        "deal": 88.3, 
        "diff": -1.7, 
        "sell": 88.3
    }, 
    "103103": {
        "buy": 88.2, 
        "count": 2.0, 
        "deal": 88.3, 
        "diff": -1.7, 
        "sell": 88.3
    }, 
    "103344": {
        "buy": 88.2, 
        "count": 1.0, 
        "deal": 88.2, 
        "diff": -1.8, 
        "sell": 88.3
    }, 
    "103545": {
        "buy": 88.2, 
        "count": 1.0, 
        "deal": 88.3, 
        "diff": -1.7, 
        "sell": 88.3
    }, 
    "103610": {
        "buy": 88.2, 
        "count": 1.0, 
        "deal": 88.3, 
        "diff": -1.7, 
        "sell": 88.3
    }, 
    "103630": {
        "buy": 88.3, 
        "count": 1.0, 
        "deal": 88.5, 
        "diff": -1.5, 
        "sell": 88.5
    }, 
    "103635": {
        "buy": 88.3, 
        "count": 2.0, 
        "deal": 88.5, 
        "diff": -1.5, 
        "sell": 88.5
    }, 
    "103640": {
        "buy": 88.5, 
        "count": 1.0, 
        "deal": 88.6, 
        "diff": -1.4, 
        "sell": 88.6
    }, 
    "103650": {
        "buy": 88.5, 
        "count": 1.0, 
        "deal": 88.5, 
        "diff": -1.5, 
        "sell": 88.6
    }, 
    "103700": {
        "buy": 88.5, 
        "count": 2.0, 
        "deal": 88.5, 
        "diff": -1.5, 
        "sell": 88.6
    }, 
    "103705": {
        "buy": 88.5, 
        "count": 1.0, 
        "deal": 88.5, 
        "diff": -1.5, 
        "sell": 88.6
    }, 
    "103720": {
        "buy": 88.3, 
        "count": 5.0, 
        "deal": 88.3, 
        "diff": -1.7, 
        "sell": 88.5
    }, 
    "103755": {
        "buy": 88.2, 
        "count": 1.0, 
        "deal": 88.2, 
        "diff": -1.8, 
        "sell": 88.3
    }, 
    "103856": {
        "buy": 88.1, 
        "count": 1.0, 
        "deal": 88.3, 
        "diff": -1.7, 
        "sell": 88.3
    }, 
    "104101": {
        "buy": 88.1, 
        "count": 1.0, 
        "deal": 88.3, 
        "diff": -1.7, 
        "sell": 88.3
    }, 
    "104201": {
        "buy": 88.2, 
        "count": 1.0, 
        "deal": 88.2, 
        "diff": -1.8, 
        "sell": 88.3
    }, 
    "104226": {
        "buy": 88.2, 
        "count": 2.0, 
        "deal": 88.2, 
        "diff": -1.8, 
        "sell": 88.3
    }, 
    "104241": {
        "buy": 88.1, 
        "count": 1.0, 
        "deal": 88.3, 
        "diff": -1.7, 
        "sell": 88.3
    }, 
    "104307": {
        "buy": 88.1, 
        "count": 4.0, 
        "deal": 88.3, 
        "diff": -1.7, 
        "sell": 88.3
    }, 
    "104312": {
        "buy": 88.3, 
        "count": 1.0, 
        "deal": 88.5, 
        "diff": -1.5, 
        "sell": 88.5
    }, 
    "104447": {
        "buy": 88.3, 
        "count": 1.0, 
        "deal": 88.4, 
        "diff": -1.6, 
        "sell": 88.4
    }, 
    "104512": {
        "buy": 88.3, 
        "count": 1.0, 
        "deal": 88.5, 
        "diff": -1.5, 
        "sell": 88.5
    }, 
    "104537": {
        "buy": 88.3, 
        "count": 10.0, 
        "deal": 88.5, 
        "diff": -1.5, 
        "sell": 88.5
    }, 
    "104543": {
        "buy": 88.3, 
        "count": 1.0, 
        "deal": 88.5, 
        "diff": -1.5, 
        "sell": 88.5
    }, 
    "104613": {
        "buy": 88.3, 
        "count": 1.0, 
        "deal": 88.3, 
        "diff": -1.7, 
        "sell": 88.5
    }, 
    "104618": {
        "buy": 88.3, 
        "count": 1.0, 
        "deal": 88.5, 
        "diff": -1.5, 
        "sell": 88.5
    }, 
    "104813": {
        "buy": 88.4, 
        "count": 3.0, 
        "deal": 88.5, 
        "diff": -1.5, 
        "sell": 88.5
    }, 
    "105024": {
        "buy": 88.4, 
        "count": 1.0, 
        "deal": 88.4, 
        "diff": -1.6, 
        "sell": 88.6
    }, 
    "105254": {
        "buy": 88.4, 
        "count": 3.0, 
        "deal": 88.4, 
        "diff": -1.6, 
        "sell": 88.6
    }, 
    "105345": {
        "buy": 88.3, 
        "count": 1.0, 
        "deal": 88.4, 
        "diff": -1.6, 
        "sell": 88.4
    }, 
    "105350": {
        "buy": 88.3, 
        "count": 1.0, 
        "deal": 88.4, 
        "diff": -1.6, 
        "sell": 88.4
    }, 
    "105400": {
        "buy": 88.3, 
        "count": 7.0, 
        "deal": 88.3, 
        "diff": -1.7, 
        "sell": 88.4
    }, 
    "105435": {
        "buy": 88.2, 
        "count": 1.0, 
        "deal": 88.2, 
        "diff": -1.8, 
        "sell": 88.4
    }, 
    "105440": {
        "buy": 88.2, 
        "count": 2.0, 
        "deal": 88.4, 
        "diff": -1.6, 
        "sell": 88.4
    }, 
    "105455": {
        "buy": 88.4, 
        "count": 4.0, 
        "deal": 88.4, 
        "diff": -1.6, 
        "sell": 88.6
    }, 
    "105746": {
        "buy": 88.3, 
        "count": 7.0, 
        "deal": 88.3, 
        "diff": -1.7, 
        "sell": 88.5
    }, 
    "105846": {
        "buy": 88.2, 
        "count": 1.0, 
        "deal": 88.2, 
        "diff": -1.8, 
        "sell": 88.3
    }, 
    "105951": {
        "buy": 88.2, 
        "count": 5.0, 
        "deal": 88.2, 
        "diff": -1.8, 
        "sell": 88.3
    }, 
    "105956": {
        "buy": 88.1, 
        "count": 1.0, 
        "deal": 88.3, 
        "diff": -1.7, 
        "sell": 88.3
    }, 
    "110016": {
        "buy": 88.1, 
        "count": 3.0, 
        "deal": 88.3, 
        "diff": -1.7, 
        "sell": 88.3
    }, 
    "110252": {
        "buy": 88.3, 
        "count": 1.0, 
        "deal": 88.3, 
        "diff": -1.7, 
        "sell": 88.6
    }, 
    "110302": {
        "buy": 88.3, 
        "count": 5.0, 
        "deal": 88.3, 
        "diff": -1.7, 
        "sell": 88.6
    }, 
    "110402": {
        "buy": 88.2, 
        "count": 5.0, 
        "deal": 88.2, 
        "diff": -1.8, 
        "sell": 88.5
    }, 
    "110639": {
        "buy": 88.3, 
        "count": 2.0, 
        "deal": 88.3, 
        "diff": -1.7, 
        "sell": 88.4
    }, 
    "110644": {
        "buy": 88.2, 
        "count": 1.0, 
        "deal": 88.3, 
        "diff": -1.7, 
        "sell": 88.4
    }, 
    "110704": {
        "buy": 88.3, 
        "count": 1.0, 
        "deal": 88.3, 
        "diff": -1.7, 
        "sell": 88.4
    }, 
    "110709": {
        "buy": 88.3, 
        "count": 1.0, 
        "deal": 88.3, 
        "diff": -1.7, 
        "sell": 88.4
    }, 
    "110759": {
        "buy": 88.2, 
        "count": 4.0, 
        "deal": 88.2, 
        "diff": -1.8, 
        "sell": 88.3
    }, 
    "111105": {
        "buy": 88.3, 
        "count": 1.0, 
        "deal": 88.3, 
        "diff": -1.7, 
        "sell": 88.5
    }, 
    "111110": {
        "buy": 88.3, 
        "count": 1.0, 
        "deal": 88.5, 
        "diff": -1.5, 
        "sell": 88.5
    }, 
    "111115": {
        "buy": 88.3, 
        "count": 1.0, 
        "deal": 88.1, 
        "diff": -1.9, 
        "sell": 88.6
    }, 
    "111155": {
        "buy": 88.1, 
        "count": 8.0, 
        "deal": 88.1, 
        "diff": -1.9, 
        "sell": 88.5
    }, 
    "111200": {
        "buy": 88.0, 
        "count": 1.0, 
        "deal": 88.5, 
        "diff": -1.5, 
        "sell": 88.5
    }, 
    "111526": {
        "buy": 88.0, 
        "count": 1.0, 
        "deal": 88.0, 
        "diff": -2.0, 
        "sell": 88.4
    }, 
    "111932": {
        "buy": 88.1, 
        "count": 1.0, 
        "deal": 88.0, 
        "diff": -2.0, 
        "sell": 88.3
    }, 
    "112132": {
        "buy": 88.0, 
        "count": 14.0, 
        "deal": 88.0, 
        "diff": -2.0, 
        "sell": 88.3
    }, 
    "112343": {
        "buy": 88.0, 
        "count": 1.0, 
        "deal": 88.0, 
        "diff": -2.0, 
        "sell": 88.3
    }, 
    "112609": {
        "buy": 88.0, 
        "count": 1.0, 
        "deal": 88.3, 
        "diff": -1.7, 
        "sell": 88.3
    }, 
    "112629": {
        "buy": 88.0, 
        "count": 1.0, 
        "deal": 88.3, 
        "diff": -1.7, 
        "sell": 88.3
    }, 
    "112719": {
        "buy": 88.0, 
        "count": 1.0, 
        "deal": 88.1, 
        "diff": -1.9, 
        "sell": 88.1
    }, 
    "112754": {
        "buy": 88.0, 
        "count": 1.0, 
        "deal": 88.0, 
        "diff": -2.0, 
        "sell": 88.3
    }, 
    "113205": {
        "buy": 88.0, 
        "count": 1.0, 
        "deal": 88.0, 
        "diff": -2.0, 
        "sell": 88.3
    }, 
    "113426": {
        "buy": 88.0, 
        "count": 15.0, 
        "deal": 88.0, 
        "diff": -2.0, 
        "sell": 88.3
    }, 
    "113431": {
        "buy": 88.0, 
        "count": 2.0, 
        "deal": 88.3, 
        "diff": -1.7, 
        "sell": 88.3
    }, 
    "113612": {
        "buy": 88.0, 
        "count": 1.0, 
        "deal": 88.0, 
        "diff": -2.0, 
        "sell": 88.2
    }, 
    "113617": {
        "buy": 88.0, 
        "count": 1.0, 
        "deal": 88.0, 
        "diff": -2.0, 
        "sell": 88.2
    }, 
    "113737": {
        "buy": 87.9, 
        "count": 1.0, 
        "deal": 88.0, 
        "diff": -2.0, 
        "sell": 88.0
    }, 
    "113757": {
        "buy": 87.9, 
        "count": 1.0, 
        "deal": 87.9, 
        "diff": -2.1, 
        "sell": 88.2
    }, 
    "113827": {
        "buy": 88.0, 
        "count": 1.0, 
        "deal": 88.2, 
        "diff": -1.8, 
        "sell": 88.2
    }, 
    "113837": {
        "buy": 88.2, 
        "count": 1.0, 
        "deal": 88.2, 
        "diff": -1.8, 
        "sell": 88.3
    }, 
    "114023": {
        "buy": 88.2, 
        "count": 1.0, 
        "deal": 88.2, 
        "diff": -1.8, 
        "sell": 88.3
    }, 
    "114038": {
        "buy": 88.2, 
        "count": 1.0, 
        "deal": 88.2, 
        "diff": -1.8, 
        "sell": 88.3
    }, 
    "114434": {
        "buy": 88.1, 
        "count": 1.0, 
        "deal": 88.1, 
        "diff": -1.9, 
        "sell": 88.3
    }, 
    "114700": {
        "buy": 88.1, 
        "count": 1.0, 
        "deal": 88.1, 
        "diff": -1.9, 
        "sell": 88.3
    }, 
    "114725": {
        "buy": 88.1, 
        "count": 1.0, 
        "deal": 88.1, 
        "diff": -1.9, 
        "sell": 88.3
    }, 
    "114845": {
        "buy": 88.0, 
        "count": 1.0, 
        "deal": 88.0, 
        "diff": -2.0, 
        "sell": 88.3
    }, 
    "114925": {
        "buy": 88.0, 
        "count": 1.0, 
        "deal": 88.0, 
        "diff": -2.0, 
        "sell": 88.2
    }, 
    "115141": {
        "buy": 88.0, 
        "count": 1.0, 
        "deal": 88.2, 
        "diff": -1.8, 
        "sell": 88.2
    }, 
    "115256": {
        "buy": 88.0, 
        "count": 1.0, 
        "deal": 88.0, 
        "diff": -2.0, 
        "sell": 88.3
    }, 
    "115527": {
        "buy": 88.0, 
        "count": 7.0, 
        "deal": 88.0, 
        "diff": -2.0, 
        "sell": 88.2
    }, 
    "115552": {
        "buy": 88.0, 
        "count": 1.0, 
        "deal": 88.0, 
        "diff": -2.0, 
        "sell": 88.2
    }, 
    "115557": {
        "buy": 88.0, 
        "count": 3.0, 
        "deal": 88.0, 
        "diff": -2.0, 
        "sell": 88.2
    }, 
    "115607": {
        "buy": 87.9, 
        "count": 1.0, 
        "deal": 87.9, 
        "diff": -2.1, 
        "sell": 88.1
    }, 
    "115612": {
        "buy": 87.9, 
        "count": 8.0, 
        "deal": 87.9, 
        "diff": -2.1, 
        "sell": 88.0
    }, 
    "115617": {
        "buy": 87.8, 
        "count": 8.0, 
        "deal": 87.8, 
        "diff": -2.2, 
        "sell": 87.9
    }, 
    "115622": {
        "buy": 87.8, 
        "count": 1.0, 
        "deal": 88.0, 
        "diff": -2.0, 
        "sell": 88.0
    }, 
    "115627": {
        "buy": 87.8, 
        "count": 3.0, 
        "deal": 87.7, 
        "diff": -2.3, 
        "sell": 88.0
    }, 
    "115632": {
        "buy": 87.7, 
        "count": 1.0, 
        "deal": 88.0, 
        "diff": -2.0, 
        "sell": 88.0
    }, 
    "115638": {
        "buy": 87.7, 
        "count": 3.0, 
        "deal": 87.7, 
        "diff": -2.3, 
        "sell": 88.0
    }, 
    "115648": {
        "buy": 87.7, 
        "count": 2.0, 
        "deal": 87.7, 
        "diff": -2.3, 
        "sell": 88.0
    }, 
    "115658": {
        "buy": 87.7, 
        "count": 2.0, 
        "deal": 87.7, 
        "diff": -2.3, 
        "sell": 88.0
    }, 
    "115703": {
        "buy": 87.7, 
        "count": 1.0, 
        "deal": 87.7, 
        "diff": -2.3, 
        "sell": 88.0
    }, 
    "120018": {
        "buy": 87.8, 
        "count": 1.0, 
        "deal": 87.8, 
        "diff": -2.2, 
        "sell": 88.0
    }, 
    "120043": {
        "buy": 87.8, 
        "count": 2.0, 
        "deal": 87.8, 
        "diff": -2.2, 
        "sell": 88.0
    }, 
    "120113": {
        "buy": 87.7, 
        "count": 1.0, 
        "deal": 87.7, 
        "diff": -2.3, 
        "sell": 87.8
    }, 
    "120118": {
        "buy": 87.7, 
        "count": 1.0, 
        "deal": 87.8, 
        "diff": -2.2, 
        "sell": 87.8
    }, 
    "120214": {
        "buy": 87.7, 
        "count": 2.0, 
        "deal": 88.0, 
        "diff": -2.0, 
        "sell": 88.0
    }, 
    "120219": {
        "buy": 87.7, 
        "count": 1.0, 
        "deal": 88.3, 
        "diff": -1.7, 
        "sell": 88.3
    }, 
    "120514": {
        "buy": 87.8, 
        "count": 1.0, 
        "deal": 87.8, 
        "diff": -2.2, 
        "sell": 88.2
    }, 
    "120524": {
        "buy": 87.8, 
        "count": 1.0, 
        "deal": 87.8, 
        "diff": -2.2, 
        "sell": 88.2
    }, 
    "120916": {
        "buy": 87.8, 
        "count": 1.0, 
        "deal": 87.8, 
        "diff": -2.2, 
        "sell": 88.1
    }, 
    "120936": {
        "buy": 87.8, 
        "count": 1.0, 
        "deal": 87.8, 
        "diff": -2.2, 
        "sell": 88.1
    }, 
    "120956": {
        "buy": 87.8, 
        "count": 5.0, 
        "deal": 87.8, 
        "diff": -2.2, 
        "sell": 88.1
    }, 
    "121031": {
        "buy": 87.7, 
        "count": 19.0, 
        "deal": 87.7, 
        "diff": -2.3, 
        "sell": 88.0
    }, 
    "121106": {
        "buy": 87.6, 
        "count": 1.0, 
        "deal": 87.7, 
        "diff": -2.3, 
        "sell": 87.7
    }, 
    "121131": {
        "buy": 87.6, 
        "count": 16.0, 
        "deal": 87.6, 
        "diff": -2.4, 
        "sell": 87.9
    }, 
    "121136": {
        "buy": 87.6, 
        "count": 1.0, 
        "deal": 87.9, 
        "diff": -2.1, 
        "sell": 87.9
    }, 
    "121347": {
        "buy": 87.6, 
        "count": 1.0, 
        "deal": 87.6, 
        "diff": -2.4, 
        "sell": 88.0
    }, 
    "121422": {
        "buy": 87.6, 
        "count": 1.0, 
        "deal": 87.6, 
        "diff": -2.4, 
        "sell": 88.0
    }, 
    "121753": {
        "buy": 87.7, 
        "count": 1.0, 
        "deal": 87.7, 
        "diff": -2.3, 
        "sell": 88.0
    }, 
    "122034": {
        "buy": 87.8, 
        "count": 2.0, 
        "deal": 87.8, 
        "diff": -2.2, 
        "sell": 88.0
    }, 
    "122039": {
        "buy": 87.8, 
        "count": 1.0, 
        "deal": 88.0, 
        "diff": -2.0, 
        "sell": 88.0
    }, 
    "122204": {
        "buy": 87.7, 
        "count": 1.0, 
        "deal": 87.7, 
        "diff": -2.3, 
        "sell": 88.0
    }, 
    "122330": {
        "buy": 87.7, 
        "count": 1.0, 
        "deal": 87.7, 
        "diff": -2.3, 
        "sell": 88.0
    }, 
    "122345": {
        "buy": 87.7, 
        "count": 2.0, 
        "deal": 87.7, 
        "diff": -2.3, 
        "sell": 87.9
    }, 
    "122616": {
        "buy": 87.7, 
        "count": 1.0, 
        "deal": 87.7, 
        "diff": -2.3, 
        "sell": 88.1
    }, 
    "123002": {
        "buy": 87.7, 
        "count": 1.0, 
        "deal": 87.9, 
        "diff": -2.1, 
        "sell": 87.9
    }, 
    "123007": {
        "buy": 87.7, 
        "count": 1.0, 
        "deal": 87.9, 
        "diff": -2.1, 
        "sell": 87.9
    }, 
    "123027": {
        "buy": 87.7, 
        "count": 1.0, 
        "deal": 87.7, 
        "diff": -2.3, 
        "sell": 88.0
    }, 
    "123112": {
        "buy": 87.8, 
        "count": 1.0, 
        "deal": 87.8, 
        "diff": -2.2, 
        "sell": 88.1
    }, 
    "123152": {
        "buy": 87.7, 
        "count": 1.0, 
        "deal": 87.7, 
        "diff": -2.3, 
        "sell": 88.1
    }, 
    "123237": {
        "buy": 87.7, 
        "count": 1.0, 
        "deal": 87.7, 
        "diff": -2.3, 
        "sell": 88.1
    }, 
    "123242": {
        "buy": 87.7, 
        "count": 1.0, 
        "deal": 87.7, 
        "diff": -2.3, 
        "sell": 88.0
    }, 
    "123302": {
        "buy": 87.7, 
        "count": 1.0, 
        "deal": 87.7, 
        "diff": -2.3, 
        "sell": 88.0
    }, 
    "123312": {
        "buy": 87.7, 
        "count": 1.0, 
        "deal": 87.7, 
        "diff": -2.3, 
        "sell": 88.0
    }, 
    "123433": {
        "buy": 87.7, 
        "count": 1.0, 
        "deal": 87.7, 
        "diff": -2.3, 
        "sell": 88.0
    }, 
    "123438": {
        "buy": 87.7, 
        "count": 1.0, 
        "deal": 88.0, 
        "diff": -2.0, 
        "sell": 88.0
    }, 
    "123724": {
        "buy": 87.7, 
        "count": 1.0, 
        "deal": 88.0, 
        "diff": -2.0, 
        "sell": 88.0
    }, 
    "123749": {
        "buy": 87.7, 
        "count": 1.0, 
        "deal": 88.0, 
        "diff": -2.0, 
        "sell": 88.0
    }, 
    "123754": {
        "buy": 88.0, 
        "count": 2.0, 
        "deal": 88.0, 
        "diff": -2.0, 
        "sell": 88.1
    }, 
    "123759": {
        "buy": 88.0, 
        "count": 2.0, 
        "deal": 88.0, 
        "diff": -2.0, 
        "sell": 88.1
    }, 
    "124145": {
        "buy": 87.9, 
        "count": 3.0, 
        "deal": 87.8, 
        "diff": -2.2, 
        "sell": 88.0
    }, 
    "124150": {
        "buy": 87.8, 
        "count": 3.0, 
        "deal": 87.8, 
        "diff": -2.2, 
        "sell": 88.0
    }, 
    "124245": {
        "buy": 87.8, 
        "count": 3.0, 
        "deal": 87.8, 
        "diff": -2.2, 
        "sell": 88.0
    }, 
    "124250": {
        "buy": 87.8, 
        "count": 1.0, 
        "deal": 87.8, 
        "diff": -2.2, 
        "sell": 88.0
    }, 
    "124255": {
        "buy": 87.8, 
        "count": 1.0, 
        "deal": 87.8, 
        "diff": -2.2, 
        "sell": 88.0
    }, 
    "124300": {
        "buy": 87.8, 
        "count": 1.0, 
        "deal": 87.8, 
        "diff": -2.2, 
        "sell": 88.0
    }, 
    "124541": {
        "buy": 87.8, 
        "count": 1.0, 
        "deal": 87.8, 
        "diff": -2.2, 
        "sell": 88.0
    }, 
    "124616": {
        "buy": 87.8, 
        "count": 1.0, 
        "deal": 87.8, 
        "diff": -2.2, 
        "sell": 88.0
    }, 
    "125052": {
        "buy": 87.8, 
        "count": 1.0, 
        "deal": 87.8, 
        "diff": -2.2, 
        "sell": 88.0
    }, 
    "125614": {
        "buy": 87.8, 
        "count": 1.0, 
        "deal": 87.8, 
        "diff": -2.2, 
        "sell": 88.0
    }, 
    "125629": {
        "buy": 87.7, 
        "count": 1.0, 
        "deal": 87.7, 
        "diff": -2.3, 
        "sell": 87.9
    }, 
    "125734": {
        "buy": 87.7, 
        "count": 5.0, 
        "deal": 87.7, 
        "diff": -2.3, 
        "sell": 87.9
    }, 
    "125739": {
        "buy": 87.7, 
        "count": 1.0, 
        "deal": 87.9, 
        "diff": -2.1, 
        "sell": 87.9
    }, 
    "125835": {
        "buy": 87.7, 
        "count": 1.0, 
        "deal": 87.9, 
        "diff": -2.1, 
        "sell": 87.9
    }, 
    "125900": {
        "buy": 87.7, 
        "count": 1.0, 
        "deal": 87.9, 
        "diff": -2.1, 
        "sell": 87.9
    }, 
    "125920": {
        "buy": 87.7, 
        "count": 1.0, 
        "deal": 87.9, 
        "diff": -2.1, 
        "sell": 87.9
    }, 
    "130000": {
        "buy": 87.7, 
        "count": 1.0, 
        "deal": 87.7, 
        "diff": -2.3, 
        "sell": 87.9
    }, 
    "130005": {
        "buy": 87.7, 
        "count": 1.0, 
        "deal": 87.7, 
        "diff": -2.3, 
        "sell": 87.9
    }, 
    "130436": {
        "buy": 87.7, 
        "count": 2.0, 
        "deal": 87.7, 
        "diff": -2.3, 
        "sell": 87.9
    }, 
    "130953": {
        "buy": 87.7, 
        "count": 1.0, 
        "deal": 87.7, 
        "diff": -2.3, 
        "sell": 87.9
    }, 
    "131333": {
        "buy": 87.8, 
        "count": 2.0, 
        "deal": 87.8, 
        "diff": -2.2, 
        "sell": 87.9
    }, 
    "131409": {
        "buy": 87.8, 
        "count": 2.0, 
        "deal": 87.9, 
        "diff": -2.1, 
        "sell": 87.9
    }, 
    "131419": {
        "buy": 87.8, 
        "count": 2.0, 
        "deal": 87.9, 
        "diff": -2.1, 
        "sell": 87.9
    }, 
    "131424": {
        "buy": 87.8, 
        "count": 1.0, 
        "deal": 87.9, 
        "diff": -2.1, 
        "sell": 87.9
    }, 
    "131434": {
        "buy": 87.8, 
        "count": 1.0, 
        "deal": 87.9, 
        "diff": -2.1, 
        "sell": 87.9
    }, 
    "131610": {
        "buy": 87.8, 
        "count": 2.0, 
        "deal": 87.8, 
        "diff": -2.2, 
        "sell": 88.0
    }, 
    "131715": {
        "buy": 87.8, 
        "count": 9.0, 
        "deal": 88.0, 
        "diff": -2.0, 
        "sell": 88.0
    }, 
    "131720": {
        "buy": 88.0, 
        "count": 1.0, 
        "deal": 88.2, 
        "diff": -1.8, 
        "sell": 88.2
    }, 
    "131730": {
        "buy": 88.0, 
        "count": 2.0, 
        "deal": 88.0, 
        "diff": -2.0, 
        "sell": 88.2
    }, 
    "131735": {
        "buy": 87.8, 
        "count": 1.0, 
        "deal": 88.0, 
        "diff": -2.0, 
        "sell": 88.0
    }, 
    "131740": {
        "buy": 87.8, 
        "count": 1.0, 
        "deal": 88.0, 
        "diff": -2.0, 
        "sell": 88.0
    }, 
    "132000": {
        "buy": 87.9, 
        "count": 1.0, 
        "deal": 87.9, 
        "diff": -2.1, 
        "sell": 88.0
    }, 
    "132146": {
        "buy": 87.9, 
        "count": 1.0, 
        "deal": 88.0, 
        "diff": -2.0, 
        "sell": 88.0
    }, 
    "132226": {
        "buy": 87.9, 
        "count": 1.0, 
        "deal": 88.0, 
        "diff": -2.0, 
        "sell": 88.0
    }, 
    "132321": {
        "buy": 87.9, 
        "count": 2.0, 
        "deal": 87.9, 
        "diff": -2.1, 
        "sell": 88.0
    }, 
    "132336": {
        "buy": 87.8, 
        "count": 1.0, 
        "deal": 88.0, 
        "diff": -2.0, 
        "sell": 88.0
    }, 
    "132401": {
        "buy": 87.8, 
        "count": 1.0, 
        "deal": 88.0, 
        "diff": -2.0, 
        "sell": 88.0
    }, 
    "132406": {
        "buy": 87.8, 
        "count": 1.0, 
        "deal": 88.0, 
        "diff": -2.0, 
        "sell": 88.0
    }, 
    "132411": {
        "buy": 87.8, 
        "count": 1.0, 
        "deal": 87.8, 
        "diff": -2.2, 
        "sell": 88.0
    }, 
    "132441": {
        "buy": 87.8, 
        "count": 1.0, 
        "deal": 87.8, 
        "diff": -2.2, 
        "sell": 88.0
    }, 
    "132451": {
        "buy": 87.8, 
        "count": 1.0, 
        "deal": 87.9, 
        "diff": -2.1, 
        "sell": 88.0
    }, 
    "133000": {
        "buy": 87.8, 
        "count": 24.0, 
        "deal": 87.8, 
        "diff": -2.2, 
        "sell": 88.0
    }
}